[{"iob":0.763,"activity":-0.0008,"bolussnooze":0.732,"basaliob":-0.115,"netbasalinsulin":-0.35,"hightempinsulin":0.2,"time":"2016-04-21T17:17:56.000Z"},{"iob":0.763,"activity":0.0001,"bolussnooze":0.617,"basaliob":-0.101,"netbasalinsulin":-0.35,"hightempinsulin":0.2,"time":"2016-04-21T17:22:56.000Z"},{"iob":0.758,"activity":0.0009,"bolussnooze":0.474,"basaliob":-0.089,"netbasalinsulin":-0.3,"hightempinsulin":0.2,"time":"2016-04-21T17:27:56.000Z"},{"iob":0.749,"activity":0.0017,"bolussnooze":0.342,"basaliob":-0.077,"netbasalinsulin":-0.25,"hightempinsulin":0.2,"time":"2016-04-21T17:32:56.000Z"},{"iob":0.737,"activity":0.0025,"bolussnooze":0.232,"basaliob":-0.065,"netbasalinsulin":-0.25,"hightempinsulin":0.2,"time":"2016-04-21T17:37:56.000Z"},{"iob":0.72,"activity":0.0034,"bolussnooze":0.143,"basaliob":-0.055,"netbasalinsulin":-0.25,"hightempinsulin":0.2,"time":"2016-04-21T17:42:56.000Z"},{"iob":0.699,"activity":0.0042,"bolussnooze":0.075,"basaliob":-0.046,"netbasalinsulin":-0.25,"hightempinsulin":0.2,"time":"2016-04-21T17:47:56.000Z"},{"iob":0.673,"activity":0.0051,"bolussnooze":0.029,"basaliob":-0.037,"netbasalinsulin":-0.25,"hightempinsulin":0.2,"time":"2016-04-21T17:52:56.000Z"},{"iob":0.643,"activity":0.006,"bolussnooze":0.004,"basaliob":-0.03,"netbasalinsulin":-0.3,"hightempinsulin":0.15,"time":"2016-04-21T17:57:56.000Z"},{"iob":0.609,"activity":0.0068,"bolussnooze":0,"basaliob":-0.023,"netbasalinsulin":-0.3,"hightempinsulin":0.15,"time":"2016-04-21T18:02:56.000Z"},{"iob":0.571,"activity":0.0077,"bolussnooze":0,"basaliob":-0.018,"netbasalinsulin":-0.35,"hightempinsulin":0.1,"time":"2016-04-21T18:07:56.000Z"},{"iob":0.528,"activity":0.0085,"bolussnooze":0,"basaliob":-0.013,"netbasalinsulin":-0.35,"hightempinsulin":0.1,"time":"2016-04-21T18:12:56.000Z"},{"iob":0.482,"activity":0.0091,"bolussnooze":0,"basaliob":-0.009,"netbasalinsulin":-0.35,"hightempinsulin":0.1,"time":"2016-04-21T18:17:56.000Z"},{"iob":0.439,"activity":0.0088,"bolussnooze":0,"basaliob":-0.006,"netbasalinsulin":-0.35,"hightempinsulin":0.1,"time":"2016-04-21T18:22:56.000Z"},{"iob":0.396,"activity":0.0085,"bolussnooze":0,"basaliob":-0.003,"netbasalinsulin":-0.3,"hightempinsulin":0.1,"time":"2016-04-21T18:27:56.000Z"},{"iob":0.356,"activity":0.0081,"bolussnooze":0,"basaliob":-0.001,"netbasalinsulin":-0.25,"hightempinsulin":0.1,"time":"2016-04-21T18:32:56.000Z"},{"iob":0.317,"activity":0.0078,"bolussnooze":0,"basaliob":0,"netbasalinsulin":-0.2,"hightempinsulin":0.1,"time":"2016-04-21T18:37:56.000Z"},{"iob":0.28,"activity":0.0074,"bolussnooze":0,"basaliob":0,"netbasalinsulin":-0.2,"hightempinsulin":0.1,"time":"2016-04-21T18:42:56.000Z"},{"iob":0.244,"activity":0.007,"bolussnooze":0,"basaliob":0.001,"netbasalinsulin":-0.15,"hightempinsulin":0.1,"time":"2016-04-21T18:47:56.000Z"},{"iob":0.211,"activity":0.0066,"bolussnooze":0,"basaliob":0.001,"netbasalinsulin":-0.1,"hightempinsulin":0.1,"time":"2016-04-21T18:52:56.000Z"},{"iob":0.181,"activity":0.0062,"bolussnooze":0,"basaliob":0,"netbasalinsulin":-0.05,"hightempinsulin":0.1,"time":"2016-04-21T18:57:56.000Z"},{"iob":0.152,"activity":0.0057,"bolussnooze":0,"basaliob":0,"netbasalinsulin":0,"hightempinsulin":0.1,"time":"2016-04-21T19:02:56.000Z"},{"iob":0.126,"activity":0.0052,"bolussnooze":0,"basaliob":0,"netbasalinsulin":0,"hightempinsulin":0.1,"time":"2016-04-21T19:07:56.000Z"},{"iob":0.103,"activity":0.0047,"bolussnooze":0,"basaliob":0,"netbasalinsulin":0,"hightempinsulin":0.1,"time":"2016-04-21T19:12:56.000Z"},{"iob":0.081,"activity":0.0043,"bolussnooze":0,"basaliob":-0.001,"netbasalinsulin":0,"hightempinsulin":0.1,"time":"2016-04-21T19:17:56.000Z"},{"iob":0.063,"activity":0.0038,"bolussnooze":0,"basaliob":-0.001,"netbasalinsulin":0,"hightempinsulin":0.1,"time":"2016-04-21T19:22:56.000Z"},{"iob":0.046,"activity":0.0033,"bolussnooze":0,"basaliob":-0.001,"netbasalinsulin":0.05,"hightempinsulin":0.1,"time":"2016-04-21T19:27:56.000Z"},{"iob":0.032,"activity":0.0028,"bolussnooze":0,"basaliob":-0.001,"netbasalinsulin":0.05,"hightempinsulin":0.1,"time":"2016-04-21T19:32:56.000Z"},{"iob":0.021,"activity":0.0023,"bolussnooze":0,"basaliob":-0.001,"netbasalinsulin":0.05,"hightempinsulin":0.1,"time":"2016-04-21T19:37:56.000Z"},{"iob":0.012,"activity":0.0018,"bolussnooze":0,"basaliob":-0.001,"netbasalinsulin":0.05,"hightempinsulin":0.1,"time":"2016-04-21T19:42:56.000Z"},{"iob":0.006,"activity":0.0013,"bolussnooze":0,"basaliob":-0.001,"netbasalinsulin":0,"hightempinsulin":0.05,"time":"2016-04-21T19:47:56.000Z"},{"iob":0.002,"activity":0.0008,"bolussnooze":0,"basaliob":0,"netbasalinsulin":0,"hightempinsulin":0.05,"time":"2016-04-21T19:52:56.000Z"},{"iob":0,"activity":0.0004,"bolussnooze":0,"basaliob":0,"netbasalinsulin":-0.05,"hightempinsulin":0,"time":"2016-04-21T19:57:56.000Z"},{"iob":0,"activity":0,"bolussnooze":0,"basaliob":0,"netbasalinsulin":-0.05,"hightempinsulin":0,"time":"2016-04-21T20:02:56.000Z"},{"iob":0,"activity":0,"bolussnooze":0,"basaliob":0,"netbasalinsulin":0,"hightempinsulin":0,"time":"2016-04-21T20:07:56.000Z"},{"iob":0,"activity":0,"bolussnooze":0,"basaliob":0,"netbasalinsulin":0,"hightempinsulin":0,"time":"2016-04-21T20:12:56.000Z"}]
