[{"iob":-0.379,"activity":-0.0014,"bolussnooze":0,"basaliob":-0.379,"netbasalinsulin":-0.25,"hightempinsulin":0.3,"time":"2017-07-05T18:05:09.000Z"},{"iob":-0.369,"activity":-0.0019,"bolussnooze":0,"basaliob":-0.369,"netbasalinsulin":-0.25,"hightempinsulin":0.3,"time":"2017-07-05T18:10:09.000Z"},{"iob":-0.357,"activity":-0.0024,"bolussnooze":0,"basaliob":-0.357,"netbasalinsulin":-0.25,"hightempinsulin":0.3,"time":"2017-07-05T18:15:09.000Z"},{"iob":-0.343,"activity":-0.0028,"bolussnooze":0,"basaliob":-0.343,"netbasalinsulin":-0.25,"hightempinsulin":0.3,"time":"2017-07-05T18:20:09.000Z"},{"iob":-0.327,"activity":-0.0032,"bolussnooze":0,"basaliob":-0.327,"netbasalinsulin":-0.25,"hightempinsulin":0.3,"time":"2017-07-05T18:25:09.000Z"},{"iob":-0.309,"activity":-0.0036,"bolussnooze":0,"basaliob":-0.309,"netbasalinsulin":-0.25,"hightempinsulin":0.3,"time":"2017-07-05T18:30:09.000Z"},{"iob":-0.29,"activity":-0.0038,"bolussnooze":0,"basaliob":-0.29,"netbasalinsulin":-0.25,"hightempinsulin":0.3,"time":"2017-07-05T18:35:09.000Z"},{"iob":-0.27,"activity":-0.004,"bolussnooze":0,"basaliob":-0.27,"netbasalinsulin":-0.25,"hightempinsulin":0.3,"time":"2017-07-05T18:40:09.000Z"},{"iob":-0.249,"activity":-0.0042,"bolussnooze":0,"basaliob":-0.249,"netbasalinsulin":-0.25,"hightempinsulin":0.3,"time":"2017-07-05T18:45:09.000Z"},{"iob":-0.227,"activity":-0.0043,"bolussnooze":0,"basaliob":-0.227,"netbasalinsulin":-0.25,"hightempinsulin":0.3,"time":"2017-07-05T18:50:09.000Z"},{"iob":-0.206,"activity":-0.0043,"bolussnooze":0,"basaliob":-0.206,"netbasalinsulin":-0.3,"hightempinsulin":0.25,"time":"2017-07-05T18:55:09.000Z"},{"iob":-0.184,"activity":-0.0042,"bolussnooze":0,"basaliob":-0.184,"netbasalinsulin":-0.3,"hightempinsulin":0.25,"time":"2017-07-05T19:00:09.000Z"},{"iob":-0.164,"activity":-0.0041,"bolussnooze":0,"basaliob":-0.164,"netbasalinsulin":-0.35,"hightempinsulin":0.2,"time":"2017-07-05T19:05:09.000Z"},{"iob":-0.145,"activity":-0.0039,"bolussnooze":0,"basaliob":-0.145,"netbasalinsulin":-0.4,"hightempinsulin":0.15,"time":"2017-07-05T19:10:09.000Z"},{"iob":-0.126,"activity":-0.0037,"bolussnooze":0,"basaliob":-0.126,"netbasalinsulin":-0.4,"hightempinsulin":0.15,"time":"2017-07-05T19:15:09.000Z"},{"iob":-0.109,"activity":-0.0035,"bolussnooze":0,"basaliob":-0.109,"netbasalinsulin":-0.45,"hightempinsulin":0.1,"time":"2017-07-05T19:20:09.000Z"},{"iob":-0.093,"activity":-0.0032,"bolussnooze":0,"basaliob":-0.093,"netbasalinsulin":-0.45,"hightempinsulin":0.1,"time":"2017-07-05T19:25:09.000Z"},{"iob":-0.078,"activity":-0.003,"bolussnooze":0,"basaliob":-0.078,"netbasalinsulin":-0.5,"hightempinsulin":0.05,"time":"2017-07-05T19:30:09.000Z"},{"iob":-0.065,"activity":-0.0027,"bolussnooze":0,"basaliob":-0.065,"netbasalinsulin":-0.55,"hightempinsulin":0,"time":"2017-07-05T19:35:09.000Z"},{"iob":-0.053,"activity":-0.0024,"bolussnooze":0,"basaliob":-0.053,"netbasalinsulin":-0.55,"hightempinsulin":0,"time":"2017-07-05T19:40:09.000Z"},{"iob":-0.042,"activity":-0.0021,"bolussnooze":0,"basaliob":-0.042,"netbasalinsulin":-0.55,"hightempinsulin":0,"time":"2017-07-05T19:45:09.000Z"},{"iob":-0.033,"activity":-0.0018,"bolussnooze":0,"basaliob":-0.033,"netbasalinsulin":-0.55,"hightempinsulin":0,"time":"2017-07-05T19:50:09.000Z"},{"iob":-0.025,"activity":-0.0015,"bolussnooze":0,"basaliob":-0.025,"netbasalinsulin":-0.5,"hightempinsulin":0,"time":"2017-07-05T19:55:09.000Z"},{"iob":-0.019,"activity":-0.0013,"bolussnooze":0,"basaliob":-0.019,"netbasalinsulin":-0.45,"hightempinsulin":0,"time":"2017-07-05T20:00:09.000Z"},{"iob":-0.013,"activity":-0.0011,"bolussnooze":0,"basaliob":-0.013,"netbasalinsulin":-0.45,"hightempinsulin":0,"time":"2017-07-05T20:05:09.000Z"},{"iob":-0.009,"activity":-0.0008,"bolussnooze":0,"basaliob":-0.009,"netbasalinsulin":-0.4,"hightempinsulin":0,"time":"2017-07-05T20:10:09.000Z"},{"iob":-0.006,"activity":-0.0006,"bolussnooze":0,"basaliob":-0.006,"netbasalinsulin":-0.35,"hightempinsulin":0,"time":"2017-07-05T20:15:09.000Z"},{"iob":-0.004,"activity":-0.0005,"bolussnooze":0,"basaliob":-0.004,"netbasalinsulin":-0.3,"hightempinsulin":0,"time":"2017-07-05T20:20:09.000Z"},{"iob":-0.002,"activity":-0.0003,"bolussnooze":0,"basaliob":-0.002,"netbasalinsulin":-0.25,"hightempinsulin":0,"time":"2017-07-05T20:25:09.000Z"},{"iob":-0.001,"activity":-0.0002,"bolussnooze":0,"basaliob":-0.001,"netbasalinsulin":-0.2,"hightempinsulin":0,"time":"2017-07-05T20:30:09.000Z"},{"iob":0,"activity":-0.0001,"bolussnooze":0,"basaliob":0,"netbasalinsulin":-0.15,"hightempinsulin":0,"time":"2017-07-05T20:35:09.000Z"},{"iob":0,"activity":-0.0001,"bolussnooze":0,"basaliob":0,"netbasalinsulin":-0.1,"hightempinsulin":0,"time":"2017-07-05T20:40:09.000Z"},{"iob":0,"activity":0,"bolussnooze":0,"basaliob":0,"netbasalinsulin":-0.05,"hightempinsulin":0,"time":"2017-07-05T20:45:09.000Z"},{"iob":0,"activity":0,"bolussnooze":0,"basaliob":0,"netbasalinsulin":0,"hightempinsulin":0,"time":"2017-07-05T20:50:09.000Z"},{"iob":0,"activity":0,"bolussnooze":0,"basaliob":0,"netbasalinsulin":0,"hightempinsulin":0,"time":"2017-07-05T20:55:09.000Z"},{"iob":0,"activity":0,"bolussnooze":0,"basaliob":0,"netbasalinsulin":0,"hightempinsulin":0,"time":"2017-07-05T21:00:09.000Z"},{"iob":0,"activity":0,"bolussnooze":0,"basaliob":0,"netbasalinsulin":0,"hightempinsulin":0,"time":"2017-07-05T21:05:09.000Z"},{"iob":0,"activity":0,"bolussnooze":0,"basaliob":0,"netbasalinsulin":0,"hightempinsulin":0,"time":"2017-07-05T21:10:09.000Z"},{"iob":0,"activity":0,"bolussnooze":0,"basaliob":0,"netbasalinsulin":0,"hightempinsulin":0,"time":"2017-07-05T21:15:09.000Z"},{"iob":0,"activity":0,"bolussnooze":0,"basaliob":0,"netbasalinsulin":0,"hightempinsulin":0,"time":"2017-07-05T21:20:09.000Z"},{"iob":0,"activity":0,"bolussnooze":0,"basaliob":0,"netbasalinsulin":0,"hightempinsulin":0,"time":"2017-07-05T21:25:09.000Z"},{"iob":0,"activity":0,"bolussnooze":0,"basaliob":0,"netbasalinsulin":0,"hightempinsulin":0,"time":"2017-07-05T21:30:09.000Z"}]
