{
  "bg": 184, 
  "temp": "absolute", 
  "snoozeBG": 144, 
  "predBGs": {
    "COB": [
      184, 
      182, 
      180, 
      177, 
      174, 
      170, 
      165, 
      159, 
      153, 
      145, 
      138, 
      131, 
      125, 
      119, 
      114, 
      109, 
      105, 
      101, 
      98, 
      95, 
      93, 
      92, 
      90, 
      89, 
      89, 
      88, 
      89, 
      89, 
      90, 
      92, 
      94, 
      96, 
      99, 
      101, 
      103, 
      106, 
      108, 
      110, 
      112, 
      114, 
      116, 
      118, 
      120
    ], 
    "aCOB": [
      184, 
      188, 
      191, 
      194, 
      195, 
      196, 
      195, 
      194, 
      191, 
      188, 
      184, 
      181, 
      177, 
      174, 
      171, 
      168, 
      166, 
      164, 
      163, 
      161, 
      160, 
      159, 
      158, 
      157, 
      157, 
      156, 
      156, 
      156, 
      156, 
      156, 
      156, 
      157
    ], 
    "IOB": [
      184, 
      182, 
      179, 
      176, 
      171, 
      165, 
      159, 
      151, 
      142, 
      133, 
      123, 
      113, 
      103, 
      93, 
      85, 
      77, 
      69, 
      62, 
      56, 
      51, 
      45, 
      41, 
      39
    ]
  }, 
  "reason": "COB: 22, Dev: 15, BGI: -5.56, ISF: 95, Target: 100; Eventual BG 120 > 100 but Min. Delta -3.00 < Exp. Delta -0.9; setting current basal of 0.6 as temp, but 28m left and 0.575 ~ req 0.6U/hr: no action required", 
  "COB": 22, 
  "eventualBG": 120, 
  "tick": -3, 
  "IOB": 1.919
}