[
  {
    "created_at": "2017-07-06T04:19:29.371Z", 
    "mmtune": {
      "scanDetails": [
        [
          "916.588", 
          5, 
          -91
        ], 
        [
          "916.612", 
          5, 
          -89
        ], 
        [
          "916.636", 
          5, 
          -88
        ], 
        [
          "916.660", 
          5, 
          -89
        ], 
        [
          "916.684", 
          5, 
          -90
        ], 
        [
          "916.708", 
          5, 
          -92
        ]
      ], 
      "setFreq": 916.636, 
      "usedDefault": false, 
      "timestamp": "2017-07-06T04:16:09.914Z"
    }, 
    "pump": {
      "battery": {
        "status": "normal", 
        "voltage": 1.57
      }, 
      "status": {
        "status": "normal", 
        "timestamp": "2017-07-06T04:16:45.565Z", 
        "bolusing": false, 
        "suspended": false
      }, 
      "reservoir": 50.725, 
      "clock": "2017-07-05T21:16:58-07:00"
    }, 
    "openaps": {
      "suggested": {
        "bg": 158, 
        "temp": "absolute", 
        "snoozeBG": 134, 
        "timestamp": "2017-07-06T04:19:24.296Z", 
        "predBGs": {
          "COB": [
            158, 
            161, 
            163, 
            165, 
            166, 
            167, 
            168, 
            168, 
            167, 
            166, 
            165, 
            162, 
            160, 
            157, 
            153, 
            149, 
            145, 
            142, 
            138, 
            135, 
            132, 
            129, 
            126, 
            123, 
            121, 
            119, 
            117, 
            115, 
            113, 
            112, 
            111, 
            110, 
            109, 
            109, 
            108
          ], 
          "aCOB": [
            158, 
            165, 
            170, 
            174, 
            176, 
            177, 
            177, 
            175, 
            172, 
            169, 
            166, 
            162, 
            158, 
            155, 
            151, 
            147, 
            143, 
            139, 
            136, 
            132, 
            129, 
            126, 
            123, 
            121, 
            118, 
            116, 
            114, 
            113, 
            111, 
            110, 
            109, 
            108, 
            107, 
            107, 
            106, 
            106, 
            106, 
            105
          ], 
          "IOB": [
            158, 
            161, 
            163, 
            164, 
            166, 
            166, 
            166, 
            166, 
            165, 
            163, 
            160, 
            157, 
            154, 
            150, 
            146, 
            142, 
            138, 
            135, 
            131, 
            128, 
            124, 
            121, 
            119, 
            116, 
            114, 
            112, 
            110, 
            108, 
            106, 
            105, 
            104, 
            103, 
            102, 
            102, 
            101
          ]
        }, 
        "reason": "COB: 5, Dev: 31, BGI: -2.14, ISF: 95, Target: 100; Eventual BG 134 >= 100, temp 2.1 >~ req 2U/hr", 
        "COB": 5, 
        "eventualBG": 134, 
        "tick": "+3", 
        "IOB": 0.578
      }, 
      "iob": {
        "netbasalinsulin": 1.05, 
        "timestamp": "2017-07-06T04:16:58.000Z", 
        "activity": 0.0045, 
        "basaliob": 0.358, 
        "hightempinsulin": 1.6, 
        "bolussnooze": 0.001, 
        "iob": 0.578
      }, 
      "enacted": {
        "bg": 150, 
        "temp": "absolute", 
        "snoozeBG": 137, 
        "recieved": true, 
        "reason": "COB: 6, Dev: 27, BGI: -2.37, ISF: 95, Target: 100; Eventual BG 137 >= 100, temp 1.35<2.1U/hr", 
        "rate": 2.1, 
        "COB": 6, 
        "eventualBG": 137, 
        "timestamp": "2017-07-06T04:09:56.161Z", 
        "duration": 30, 
        "tick": "+3", 
        "IOB": 0.569
      }
    }, 
    "uploader": {
      "battery": 100, 
      "batteryVoltage": 4394
    }, 
    "device": "openaps://indy-e3", 
    "_id": "595dba5164a18234af6c6514"
  }
]