[
  {
    "filtered": 145000, 
    "direction": "Flat", 
    "noise": 1, 
    "raw": 136, 
    "type": "sgv", 
    "_id": "5733535665110bbfc192f0f2", 
    "sysTime": "2016-05-11T08:43:39.091-0700", 
    "dateString": "2016-05-11T08:43:39.091-0700", 
    "sgv": 128, 
    "device": "xDrip-DexcomShare", 
    "xDrip_filtered": 145, 
    "unfiltered": 153000, 
    "xDrip_raw": 153, 
    "date": 1462981419091, 
    "rssi": 100, 
    "xDrip_calculated_current_slope": 2.0063400345090488e-05, 
    "xDrip_age_adjusted_raw_value": 153, 
    "xDrip_calculated_value": 128
  }, 
  {
    "filtered": 142000, 
    "direction": "Flat", 
    "noise": 1, 
    "raw": 126, 
    "type": "sgv", 
    "_id": "5733522965110bbfc192f0f1", 
    "sysTime": "2016-05-11T08:38:40.039-0700", 
    "dateString": "2016-05-11T08:38:40.039-0700", 
    "sgv": 122, 
    "device": "xDrip-DexcomShare", 
    "xDrip_filtered": 142, 
    "unfiltered": 146000, 
    "xDrip_raw": 146, 
    "date": 1462981120039, 
    "rssi": 100, 
    "xDrip_calculated_current_slope": 9.9795751362212e-06, 
    "xDrip_age_adjusted_raw_value": 146, 
    "xDrip_calculated_value": 122
  }, 
  {
    "filtered": 139000, 
    "direction": "Flat", 
    "noise": 1, 
    "raw": 123, 
    "type": "sgv", 
    "_id": "573350f765110bbfc192f0ef", 
    "sysTime": "2016-05-11T08:33:39.425-0700", 
    "dateString": "2016-05-11T08:33:39.425-0700", 
    "sgv": 119, 
    "device": "xDrip-DexcomShare", 
    "xDrip_filtered": 139, 
    "unfiltered": 143000, 
    "xDrip_raw": 143, 
    "date": 1462980819425, 
    "rssi": 100, 
    "xDrip_calculated_current_slope": 1.3336623033681642e-05, 
    "xDrip_age_adjusted_raw_value": 143, 
    "xDrip_calculated_value": 119
  }, 
  {
    "filtered": 133000, 
    "direction": "Flat", 
    "noise": 1, 
    "raw": 121, 
    "type": "sgv", 
    "_id": "57334fcf65110bbfc192f0ec", 
    "sysTime": "2016-05-11T08:28:39.499-0700", 
    "dateString": "2016-05-11T08:28:39.499-0700", 
    "sgv": 115, 
    "device": "xDrip-DexcomShare", 
    "xDrip_filtered": 133, 
    "unfiltered": 139000, 
    "xDrip_raw": 139, 
    "date": 1462980519499, 
    "rssi": 100, 
    "xDrip_calculated_current_slope": 6.649289855843396e-06, 
    "xDrip_age_adjusted_raw_value": 139, 
    "xDrip_calculated_value": 115
  }, 
  {
    "filtered": 126000, 
    "direction": "FortyFiveUp", 
    "noise": 1, 
    "raw": 123, 
    "type": "sgv", 
    "_id": "57334ea465110bbfc192f0eb", 
    "sysTime": "2016-05-11T08:23:38.715-0700", 
    "dateString": "2016-05-11T08:23:38.715-0700", 
    "sgv": 113, 
    "device": "xDrip-DexcomShare", 
    "xDrip_filtered": 126, 
    "unfiltered": 136000, 
    "xDrip_raw": 136, 
    "date": 1462980218715, 
    "rssi": 100, 
    "xDrip_calculated_current_slope": 1.3371084361514008e-05, 
    "xDrip_age_adjusted_raw_value": 136, 
    "xDrip_calculated_value": 113
  }, 
  {
    "filtered": 119000, 
    "direction": "FortyFiveUp", 
    "noise": 1, 
    "raw": 123, 
    "type": "sgv", 
    "_id": "57334d9e65110bbfc192f0e9", 
    "sysTime": "2016-05-11T08:18:39.562-0700", 
    "dateString": "2016-05-11T08:18:39.562-0700", 
    "sgv": 109, 
    "device": "xDrip-DexcomShare", 
    "xDrip_filtered": 119, 
    "unfiltered": 133000, 
    "xDrip_raw": 133, 
    "date": 1462979919562, 
    "rssi": 100, 
    "xDrip_calculated_current_slope": 2.6592827249670084e-05, 
    "xDrip_age_adjusted_raw_value": 133, 
    "xDrip_calculated_value": 109
  }, 
  {
    "filtered": 115000, 
    "direction": "Flat", 
    "noise": 1, 
    "raw": 110, 
    "type": "sgv", 
    "_id": "57334c4965110bbfc192f0e8", 
    "sysTime": "2016-05-11T08:13:38.729-0700", 
    "dateString": "2016-05-11T08:13:38.729-0700", 
    "sgv": 101, 
    "device": "xDrip-DexcomShare", 
    "xDrip_filtered": 115, 
    "unfiltered": 124000, 
    "xDrip_raw": 124, 
    "date": 1462979618729, 
    "rssi": 100, 
    "xDrip_calculated_current_slope": 2.3356923826397994e-05, 
    "xDrip_age_adjusted_raw_value": 124, 
    "xDrip_calculated_value": 101
  }, 
  {
    "filtered": 113000, 
    "direction": "Flat", 
    "noise": 1, 
    "raw": 98, 
    "type": "sgv", 
    "_id": "57334b4465110bbfc192f0e7", 
    "sysTime": "2016-05-11T08:08:39.032-0700", 
    "dateString": "2016-05-11T08:08:39.032-0700", 
    "sgv": 94, 
    "device": "xDrip-DexcomShare", 
    "xDrip_filtered": 113, 
    "unfiltered": 117000, 
    "xDrip_raw": 117, 
    "date": 1462979319032, 
    "rssi": 100, 
    "xDrip_calculated_current_slope": 1.0009008107296568e-05, 
    "xDrip_age_adjusted_raw_value": 117, 
    "xDrip_calculated_value": 94
  }, 
  {
    "filtered": 114000, 
    "direction": "Flat", 
    "noise": 1, 
    "raw": 90, 
    "type": "sgv", 
    "_id": "573349f265110bbfc192f0e5", 
    "sysTime": "2016-05-11T08:03:39.302-0700", 
    "dateString": "2016-05-11T08:03:39.302-0700", 
    "sgv": 91, 
    "device": "xDrip-DexcomShare", 
    "xDrip_filtered": 114, 
    "unfiltered": 113000, 
    "xDrip_raw": 113, 
    "date": 1462979019302, 
    "rssi": 100, 
    "xDrip_calculated_current_slope": 0, 
    "xDrip_age_adjusted_raw_value": 113, 
    "xDrip_calculated_value": 91
  }, 
  {
    "filtered": 116000, 
    "direction": "Flat", 
    "noise": 1, 
    "raw": 88, 
    "type": "sgv", 
    "_id": "573348ea65110bbfc192f0e4", 
    "sysTime": "2016-05-11T07:58:39.694-0700", 
    "dateString": "2016-05-11T07:58:39.694-0700", 
    "sgv": 91, 
    "device": "xDrip-DexcomShare", 
    "xDrip_filtered": 116, 
    "unfiltered": 113000, 
    "xDrip_raw": 113, 
    "date": 1462978719694, 
    "rssi": 100, 
    "xDrip_calculated_current_slope": -3.326779577565529e-06, 
    "xDrip_age_adjusted_raw_value": 113, 
    "xDrip_calculated_value": 91
  }
]