{
  "device": "openaps://indy-e3", 
  "pump": {
    "battery": {
      "status": "normal", 
      "voltage": 1.41
    }, 
    "status": {
      "status": "normal", 
      "timestamp": "2016-05-20T03:43:10.000Z", 
      "bolusing": false, 
      "suspended": false
    }, 
    "reservoir": 54.55, 
    "clock": "2016-05-19T20:42:34-07:00"
  }, 
  "openaps": {
    "suggested": {
      "bg": 147, 
      "temp": "absolute", 
      "snoozeBG": 112, 
      "timestamp": "2016-05-20T03:44:23.000Z", 
      "predBGs": {
        "COB": [
          147, 
          153, 
          157, 
          161, 
          163, 
          165, 
          165, 
          165, 
          164, 
          163, 
          161, 
          160, 
          158, 
          156, 
          154, 
          152, 
          149, 
          146, 
          143, 
          140, 
          137, 
          134, 
          131, 
          128, 
          125, 
          122, 
          120, 
          119, 
          118, 
          117, 
          116, 
          115, 
          114, 
          114, 
          113, 
          113, 
          112
        ], 
        "aCOB": [
          147, 
          152, 
          156, 
          159, 
          161, 
          162, 
          162, 
          161, 
          160, 
          158, 
          157, 
          155, 
          154, 
          152, 
          150, 
          148, 
          145, 
          143, 
          140, 
          138, 
          135, 
          133, 
          130, 
          128, 
          125, 
          123, 
          121, 
          119, 
          118, 
          117, 
          116, 
          115, 
          115, 
          114, 
          113
        ], 
        "IOB": [
          147, 
          152, 
          156, 
          158, 
          159, 
          158, 
          156, 
          152, 
          148, 
          143, 
          137, 
          131, 
          124, 
          118, 
          111, 
          105, 
          99, 
          93, 
          88, 
          83, 
          79, 
          75, 
          71, 
          67, 
          65, 
          62, 
          60, 
          59, 
          57, 
          56, 
          55, 
          55, 
          54, 
          53, 
          53, 
          52
        ]
      }, 
      "reason": "COB: 25, Dev: 65, BGI: -4.76, ISF: 80, Target: 115; Eventual BG 112<115, but Avg. Delta 6.00 > Exp. Delta -3.6, temp 0.675 ~ req 0.7U/hr", 
      "eventualBG": 112, 
      "tick": "+6"
    }, 
    "iob": [
      {
        "netbasalinsulin": -0.25, 
        "activity": 0.0119, 
        "basaliob": 0.027, 
        "time": "2016-05-20T03:42:34.000Z", 
        "hightempinsulin": 0.45, 
        "bolussnooze": 0, 
        "iob": 1.475
      }, 
      {
        "netbasalinsulin": -0.1, 
        "activity": 0.0132, 
        "basaliob": 0.127, 
        "time": "2016-05-20T03:47:34.000Z", 
        "hightempinsulin": 0.55, 
        "bolussnooze": 0, 
        "iob": 1.509
      }, 
      {
        "netbasalinsulin": 0, 
        "activity": 0.0146, 
        "basaliob": 0.177, 
        "time": "2016-05-20T03:52:34.000Z", 
        "hightempinsulin": 0.6, 
        "bolussnooze": 0, 
        "iob": 1.486
      }, 
      {
        "netbasalinsulin": 0.15, 
        "activity": 0.016, 
        "basaliob": 0.275, 
        "time": "2016-05-20T03:57:34.000Z", 
        "hightempinsulin": 0.7, 
        "bolussnooze": 0, 
        "iob": 1.506
      }, 
      {
        "netbasalinsulin": 0.25, 
        "activity": 0.0175, 
        "basaliob": 0.323, 
        "time": "2016-05-20T04:02:34.000Z", 
        "hightempinsulin": 0.75, 
        "bolussnooze": 0, 
        "iob": 1.469
      }, 
      {
        "netbasalinsulin": 0.45, 
        "activity": 0.019, 
        "basaliob": 0.42, 
        "time": "2016-05-20T04:07:34.000Z", 
        "hightempinsulin": 0.85, 
        "bolussnooze": 0, 
        "iob": 1.474
      }, 
      {
        "netbasalinsulin": 0.5, 
        "activity": 0.0203, 
        "basaliob": 0.415, 
        "time": "2016-05-20T04:12:34.000Z", 
        "hightempinsulin": 0.85, 
        "bolussnooze": 0, 
        "iob": 1.372
      }, 
      {
        "netbasalinsulin": 0.55, 
        "activity": 0.0198, 
        "basaliob": 0.408, 
        "time": "2016-05-20T04:17:34.000Z", 
        "hightempinsulin": 0.85, 
        "bolussnooze": 0, 
        "iob": 1.273
      }, 
      {
        "netbasalinsulin": 0.6, 
        "activity": 0.0192, 
        "basaliob": 0.399, 
        "time": "2016-05-20T04:22:34.000Z", 
        "hightempinsulin": 0.85, 
        "bolussnooze": 0, 
        "iob": 1.177
      }, 
      {
        "netbasalinsulin": 0.6, 
        "activity": 0.0186, 
        "basaliob": 0.389, 
        "time": "2016-05-20T04:27:34.000Z", 
        "hightempinsulin": 0.85, 
        "bolussnooze": 0, 
        "iob": 1.084
      }, 
      {
        "netbasalinsulin": 0.6, 
        "activity": 0.0179, 
        "basaliob": 0.377, 
        "time": "2016-05-20T04:32:34.000Z", 
        "hightempinsulin": 0.85, 
        "bolussnooze": 0, 
        "iob": 0.995
      }, 
      {
        "netbasalinsulin": 0.6, 
        "activity": 0.0173, 
        "basaliob": 0.364, 
        "time": "2016-05-20T04:37:34.000Z", 
        "hightempinsulin": 0.85, 
        "bolussnooze": 0, 
        "iob": 0.908
      }, 
      {
        "netbasalinsulin": 0.6, 
        "activity": 0.0167, 
        "basaliob": 0.349, 
        "time": "2016-05-20T04:42:34.000Z", 
        "hightempinsulin": 0.85, 
        "bolussnooze": 0, 
        "iob": 0.824
      }, 
      {
        "netbasalinsulin": 0.55, 
        "activity": 0.0161, 
        "basaliob": 0.333, 
        "time": "2016-05-20T04:47:34.000Z", 
        "hightempinsulin": 0.8, 
        "bolussnooze": 0, 
        "iob": 0.744
      }, 
      {
        "netbasalinsulin": 0.55, 
        "activity": 0.0154, 
        "basaliob": 0.315, 
        "time": "2016-05-20T04:52:34.000Z", 
        "hightempinsulin": 0.8, 
        "bolussnooze": 0, 
        "iob": 0.667
      }, 
      {
        "netbasalinsulin": 0.5, 
        "activity": 0.0148, 
        "basaliob": 0.296, 
        "time": "2016-05-20T04:57:34.000Z", 
        "hightempinsulin": 0.75, 
        "bolussnooze": 0, 
        "iob": 0.593
      }, 
      {
        "netbasalinsulin": 0.45, 
        "activity": 0.014, 
        "basaliob": 0.276, 
        "time": "2016-05-20T05:02:34.000Z", 
        "hightempinsulin": 0.7, 
        "bolussnooze": 0, 
        "iob": 0.523
      }, 
      {
        "netbasalinsulin": 0.4, 
        "activity": 0.0132, 
        "basaliob": 0.255, 
        "time": "2016-05-20T05:07:34.000Z", 
        "hightempinsulin": 0.65, 
        "bolussnooze": 0, 
        "iob": 0.457
      }, 
      {
        "netbasalinsulin": 0.35, 
        "activity": 0.0124, 
        "basaliob": 0.234, 
        "time": "2016-05-20T05:12:34.000Z", 
        "hightempinsulin": 0.6, 
        "bolussnooze": 0, 
        "iob": 0.395
      }, 
      {
        "netbasalinsulin": 0.25, 
        "activity": 0.0114, 
        "basaliob": 0.213, 
        "time": "2016-05-20T05:17:34.000Z", 
        "hightempinsulin": 0.5, 
        "bolussnooze": 0, 
        "iob": 0.337
      }, 
      {
        "netbasalinsulin": 0.25, 
        "activity": 0.0104, 
        "basaliob": 0.193, 
        "time": "2016-05-20T05:22:34.000Z", 
        "hightempinsulin": 0.5, 
        "bolussnooze": 0, 
        "iob": 0.285
      }, 
      {
        "netbasalinsulin": 0.3, 
        "activity": 0.0094, 
        "basaliob": 0.173, 
        "time": "2016-05-20T05:27:34.000Z", 
        "hightempinsulin": 0.5, 
        "bolussnooze": 0, 
        "iob": 0.238
      }, 
      {
        "netbasalinsulin": 0.3, 
        "activity": 0.0083, 
        "basaliob": 0.154, 
        "time": "2016-05-20T05:32:34.000Z", 
        "hightempinsulin": 0.5, 
        "bolussnooze": 0, 
        "iob": 0.197
      }, 
      {
        "netbasalinsulin": 0.35, 
        "activity": 0.0072, 
        "basaliob": 0.135, 
        "time": "2016-05-20T05:37:34.000Z", 
        "hightempinsulin": 0.5, 
        "bolussnooze": 0, 
        "iob": 0.161
      }, 
      {
        "netbasalinsulin": 0.35, 
        "activity": 0.0061, 
        "basaliob": 0.118, 
        "time": "2016-05-20T05:42:34.000Z", 
        "hightempinsulin": 0.5, 
        "bolussnooze": 0, 
        "iob": 0.13
      }, 
      {
        "netbasalinsulin": 0.4, 
        "activity": 0.005, 
        "basaliob": 0.101, 
        "time": "2016-05-20T05:47:34.000Z", 
        "hightempinsulin": 0.5, 
        "bolussnooze": 0, 
        "iob": 0.105
      }, 
      {
        "netbasalinsulin": 0.45, 
        "activity": 0.0039, 
        "basaliob": 0.086, 
        "time": "2016-05-20T05:52:34.000Z", 
        "hightempinsulin": 0.5, 
        "bolussnooze": 0, 
        "iob": 0.086
      }, 
      {
        "netbasalinsulin": 0.5, 
        "activity": 0.0028, 
        "basaliob": 0.072, 
        "time": "2016-05-20T05:57:34.000Z", 
        "hightempinsulin": 0.5, 
        "bolussnooze": 0, 
        "iob": 0.072
      }, 
      {
        "netbasalinsulin": 0.5, 
        "activity": 0.0026, 
        "basaliob": 0.059, 
        "time": "2016-05-20T06:02:34.000Z", 
        "hightempinsulin": 0.5, 
        "bolussnooze": 0, 
        "iob": 0.059
      }, 
      {
        "netbasalinsulin": 0.5, 
        "activity": 0.0023, 
        "basaliob": 0.047, 
        "time": "2016-05-20T06:07:34.000Z", 
        "hightempinsulin": 0.5, 
        "bolussnooze": 0, 
        "iob": 0.047
      }, 
      {
        "netbasalinsulin": 0.5, 
        "activity": 0.002, 
        "basaliob": 0.037, 
        "time": "2016-05-20T06:12:34.000Z", 
        "hightempinsulin": 0.5, 
        "bolussnooze": 0, 
        "iob": 0.037
      }, 
      {
        "netbasalinsulin": 0.5, 
        "activity": 0.0018, 
        "basaliob": 0.028, 
        "time": "2016-05-20T06:17:34.000Z", 
        "hightempinsulin": 0.5, 
        "bolussnooze": 0, 
        "iob": 0.028
      }, 
      {
        "netbasalinsulin": 0.5, 
        "activity": 0.0015, 
        "basaliob": 0.021, 
        "time": "2016-05-20T06:22:34.000Z", 
        "hightempinsulin": 0.5, 
        "bolussnooze": 0, 
        "iob": 0.021
      }, 
      {
        "netbasalinsulin": 0.5, 
        "activity": 0.0012, 
        "basaliob": 0.015, 
        "time": "2016-05-20T06:27:34.000Z", 
        "hightempinsulin": 0.5, 
        "bolussnooze": 0, 
        "iob": 0.015
      }, 
      {
        "netbasalinsulin": 0.45, 
        "activity": 0.001, 
        "basaliob": 0.01, 
        "time": "2016-05-20T06:32:34.000Z", 
        "hightempinsulin": 0.45, 
        "bolussnooze": 0, 
        "iob": 0.01
      }, 
      {
        "netbasalinsulin": 0.45, 
        "activity": 0.0008, 
        "basaliob": 0.006, 
        "time": "2016-05-20T06:37:34.000Z", 
        "hightempinsulin": 0.45, 
        "bolussnooze": 0, 
        "iob": 0.006
      }
    ], 
    "enacted": {
      "bg": 141, 
      "temp": "absolute", 
      "snoozeBG": 130, 
      "recieved": true, 
      "predBGs": {
        "COB": [
          141, 
          147, 
          151, 
          155, 
          158, 
          159, 
          160, 
          160, 
          159, 
          158, 
          157, 
          156, 
          155, 
          153, 
          152, 
          150, 
          149, 
          147, 
          146, 
          144, 
          143, 
          141, 
          139, 
          137, 
          135, 
          134, 
          132, 
          131, 
          131, 
          131, 
          130
        ], 
        "aCOB": [
          141, 
          146, 
          151, 
          154, 
          157, 
          159, 
          159, 
          159, 
          158, 
          157, 
          156, 
          155, 
          153, 
          152, 
          151, 
          149, 
          148, 
          146, 
          145, 
          143, 
          142, 
          140, 
          139, 
          137, 
          135, 
          134, 
          132, 
          131, 
          131, 
          131, 
          130
        ], 
        "IOB": [
          141, 
          146, 
          150, 
          152, 
          153, 
          153, 
          151, 
          148, 
          144, 
          139, 
          133, 
          127, 
          121, 
          115, 
          109, 
          103, 
          98, 
          94, 
          89, 
          86, 
          82, 
          79, 
          76, 
          74, 
          72, 
          70, 
          68, 
          67, 
          67, 
          67, 
          66
        ]
      }, 
      "reason": "COB: 25, Dev: 61, BGI: -4.24, ISF: 80, Target: 115; Eventual BG 130>=115, temp 0.85<1.075U/hr", 
      "rate": 1.05, 
      "eventualBG": 130, 
      "timestamp": "2016-05-20T03:39:10.000Z", 
      "duration": 30, 
      "tick": "+6"
    }
  }, 
  "mmtune": {
    "scanDetails": [
      [
        "916.560", 
        5, 
        -53
      ], 
      [
        "916.580", 
        5, 
        -45
      ], 
      [
        "916.600", 
        5, 
        -44
      ], 
      [
        "916.620", 
        5, 
        -43
      ], 
      [
        "916.640", 
        5, 
        -44
      ], 
      [
        "916.660", 
        5, 
        -43
      ], 
      [
        "916.680", 
        5, 
        -44
      ], 
      [
        "916.700", 
        5, 
        -47
      ]
    ], 
    "setFreq": 916.66, 
    "timestamp": "2016-05-20T03:42:52.000Z", 
    "usedDefault": false
  }
}