{
  "device": "openaps://indy-e3", 
  "pump": {
    "battery": {
      "status": "normal", 
      "voltage": 1.5
    }, 
    "status": {
      "status": "normal", 
      "timestamp": "2016-05-18T05:01:02.000Z", 
      "bolusing": false, 
      "suspended": false
    }, 
    "reservoir": 100.8, 
    "clock": "2016-05-17T22:00:25-07:00"
  }, 
  "openaps": {
    "enacted": {
      "bg": 105, 
      "temp": "absolute", 
      "snoozeBG": 97, 
      "recieved": true, 
      "predBGs": {
        "COB": [
          105, 
          103, 
          101, 
          99, 
          98, 
          97, 
          97, 
          97, 
          98, 
          98, 
          100, 
          101, 
          104, 
          107, 
          110, 
          114, 
          118, 
          122, 
          126, 
          130, 
          134, 
          138, 
          142, 
          146, 
          149, 
          152, 
          156, 
          159, 
          162, 
          165, 
          168, 
          171, 
          174, 
          176, 
          179, 
          181, 
          183
        ], 
        "aCOB": [
          105, 
          109, 
          114, 
          118, 
          123, 
          128, 
          133, 
          138, 
          144, 
          149, 
          155, 
          161, 
          167, 
          173, 
          180, 
          187, 
          194, 
          201, 
          207, 
          214, 
          219, 
          225, 
          230, 
          235, 
          239, 
          243, 
          246, 
          250, 
          253, 
          255, 
          258, 
          260, 
          261, 
          262, 
          263, 
          264
        ], 
        "IOB": [
          105, 
          102, 
          100, 
          98, 
          96, 
          94, 
          92, 
          91, 
          89, 
          88, 
          87, 
          86, 
          86, 
          86, 
          86, 
          87, 
          89, 
          90, 
          92, 
          94, 
          95, 
          96, 
          98, 
          99, 
          100, 
          101, 
          101, 
          102, 
          103, 
          104, 
          104, 
          105, 
          106, 
          106, 
          106, 
          107
        ]
      }, 
      "reason": "COB: 38, Dev: 19, BGI: -5.44, ISF: 75.5, Target: 115; 183-97 in range: no temp required; setting current basal of 0.74 as temp", 
      "rate": 0.75, 
      "eventualBG": 183, 
      "timestamp": "2016-05-18T04:54:41.000Z", 
      "duration": 30, 
      "tick": "+2"
    }
  }, 
  "mmtune": {
    "scanDetails": [
      [
        "916.600", 
        2, 
        -98
      ], 
      [
        "916.620", 
        5, 
        -96
      ], 
      [
        "916.640", 
        5, 
        -96
      ], 
      [
        "916.660", 
        5, 
        -95
      ], 
      [
        "916.680", 
        5, 
        -96
      ]
    ], 
    "setFreq": 916.66, 
    "timestamp": "2016-05-18T05:00:52.000Z", 
    "usedDefault": false
  }
}