{
  "device": "openaps://indy-e3", 
  "pump": {
    "battery": {
      "status": "normal", 
      "voltage": 1.4
    }, 
    "status": {
      "status": "normal", 
      "timestamp": "2016-05-20T04:11:45.000Z", 
      "bolusing": false, 
      "suspended": false
    }, 
    "reservoir": 53.975, 
    "clock": "2016-05-19T21:11:09-07:00"
  }, 
  "openaps": {
    "suggested": {
      "bg": 180, 
      "temp": "absolute", 
      "snoozeBG": 158, 
      "timestamp": "2016-05-20T04:13:02.000Z", 
      "predBGs": {
        "COB": [
          180, 
          183, 
          186, 
          188, 
          190, 
          192, 
          193, 
          194, 
          195, 
          195, 
          195, 
          194, 
          194, 
          192, 
          191, 
          189, 
          187, 
          185, 
          183, 
          180, 
          178, 
          175, 
          173, 
          171, 
          169, 
          167, 
          166, 
          165, 
          163, 
          162, 
          161, 
          161, 
          160, 
          159, 
          159, 
          159, 
          158
        ], 
        "aCOB": [
          180, 
          182, 
          183, 
          184, 
          185, 
          186, 
          187, 
          187, 
          187, 
          187, 
          187, 
          187, 
          186, 
          185, 
          184, 
          183, 
          182, 
          180, 
          179, 
          177, 
          176, 
          175, 
          173, 
          172, 
          170, 
          168, 
          167, 
          165, 
          164, 
          163, 
          162, 
          161, 
          161, 
          160, 
          160, 
          159
        ], 
        "IOB": [
          180, 
          183, 
          184, 
          186, 
          186, 
          186, 
          184, 
          183, 
          180, 
          177, 
          172, 
          167, 
          162, 
          156, 
          151, 
          146, 
          142, 
          137, 
          133, 
          130, 
          127, 
          124, 
          122, 
          120, 
          118, 
          116, 
          115, 
          114, 
          112, 
          111, 
          110, 
          110, 
          109, 
          108, 
          108, 
          108, 
          107
        ]
      }, 
      "rate": 1.75, 
      "reason": "COB: 24, Dev: 69, BGI: -7.88, ISF: 80, Target: 115; Eventual BG 158>=115, temp 1.35<1.775U/hr", 
      "eventualBG": 158, 
      "duration": 30, 
      "tick": "+6"
    }, 
    "iob": [
      {
        "netbasalinsulin": 0.35, 
        "activity": 0.0197, 
        "basaliob": 0.323, 
        "time": "2016-05-20T04:11:09.000Z", 
        "hightempinsulin": 0.75, 
        "bolussnooze": 0, 
        "iob": 1.307
      }, 
      {
        "netbasalinsulin": 0.5, 
        "activity": 0.0194, 
        "basaliob": 0.369, 
        "time": "2016-05-20T04:16:09.000Z", 
        "hightempinsulin": 0.8, 
        "bolussnooze": 0, 
        "iob": 1.26
      }, 
      {
        "netbasalinsulin": 0.6, 
        "activity": 0.0188, 
        "basaliob": 0.414, 
        "time": "2016-05-20T04:21:09.000Z", 
        "hightempinsulin": 0.85, 
        "bolussnooze": 0, 
        "iob": 1.216
      }, 
      {
        "netbasalinsulin": 0.65, 
        "activity": 0.0182, 
        "basaliob": 0.457, 
        "time": "2016-05-20T04:26:09.000Z", 
        "hightempinsulin": 0.9, 
        "bolussnooze": 0, 
        "iob": 1.175
      }, 
      {
        "netbasalinsulin": 0.7, 
        "activity": 0.0177, 
        "basaliob": 0.498, 
        "time": "2016-05-20T04:31:09.000Z", 
        "hightempinsulin": 0.95, 
        "bolussnooze": 0, 
        "iob": 1.137
      }, 
      {
        "netbasalinsulin": 0.8, 
        "activity": 0.0172, 
        "basaliob": 0.587, 
        "time": "2016-05-20T04:36:09.000Z", 
        "hightempinsulin": 1.05, 
        "bolussnooze": 0, 
        "iob": 1.151
      }, 
      {
        "netbasalinsulin": 0.8, 
        "activity": 0.0167, 
        "basaliob": 0.573, 
        "time": "2016-05-20T04:41:09.000Z", 
        "hightempinsulin": 1.05, 
        "bolussnooze": 0, 
        "iob": 1.067
      }, 
      {
        "netbasalinsulin": 0.8, 
        "activity": 0.0162, 
        "basaliob": 0.557, 
        "time": "2016-05-20T04:46:09.000Z", 
        "hightempinsulin": 1.05, 
        "bolussnooze": 0, 
        "iob": 0.986
      }, 
      {
        "netbasalinsulin": 0.75, 
        "activity": 0.0157, 
        "basaliob": 0.54, 
        "time": "2016-05-20T04:51:09.000Z", 
        "hightempinsulin": 1, 
        "bolussnooze": 0, 
        "iob": 0.908
      }, 
      {
        "netbasalinsulin": 0.7, 
        "activity": 0.0152, 
        "basaliob": 0.52, 
        "time": "2016-05-20T04:56:09.000Z", 
        "hightempinsulin": 0.95, 
        "bolussnooze": 0, 
        "iob": 0.832
      }, 
      {
        "netbasalinsulin": 0.65, 
        "activity": 0.0147, 
        "basaliob": 0.498, 
        "time": "2016-05-20T05:01:09.000Z", 
        "hightempinsulin": 0.9, 
        "bolussnooze": 0, 
        "iob": 0.758
      }, 
      {
        "netbasalinsulin": 0.6, 
        "activity": 0.0141, 
        "basaliob": 0.474, 
        "time": "2016-05-20T05:06:09.000Z", 
        "hightempinsulin": 0.85, 
        "bolussnooze": 0, 
        "iob": 0.687
      }, 
      {
        "netbasalinsulin": 0.55, 
        "activity": 0.0136, 
        "basaliob": 0.448, 
        "time": "2016-05-20T05:11:09.000Z", 
        "hightempinsulin": 0.8, 
        "bolussnooze": 0, 
        "iob": 0.62
      }, 
      {
        "netbasalinsulin": 0.5, 
        "activity": 0.013, 
        "basaliob": 0.421, 
        "time": "2016-05-20T05:16:09.000Z", 
        "hightempinsulin": 0.75, 
        "bolussnooze": 0, 
        "iob": 0.555
      }, 
      {
        "netbasalinsulin": 0.45, 
        "activity": 0.0123, 
        "basaliob": 0.392, 
        "time": "2016-05-20T05:21:09.000Z", 
        "hightempinsulin": 0.7, 
        "bolussnooze": 0, 
        "iob": 0.493
      }, 
      {
        "netbasalinsulin": 0.45, 
        "activity": 0.0116, 
        "basaliob": 0.362, 
        "time": "2016-05-20T05:26:09.000Z", 
        "hightempinsulin": 0.7, 
        "bolussnooze": 0, 
        "iob": 0.435
      }, 
      {
        "netbasalinsulin": 0.5, 
        "activity": 0.0108, 
        "basaliob": 0.332, 
        "time": "2016-05-20T05:31:09.000Z", 
        "hightempinsulin": 0.7, 
        "bolussnooze": 0, 
        "iob": 0.381
      }, 
      {
        "netbasalinsulin": 0.5, 
        "activity": 0.0099, 
        "basaliob": 0.301, 
        "time": "2016-05-20T05:36:09.000Z", 
        "hightempinsulin": 0.7, 
        "bolussnooze": 0, 
        "iob": 0.331
      }, 
      {
        "netbasalinsulin": 0.55, 
        "activity": 0.0089, 
        "basaliob": 0.271, 
        "time": "2016-05-20T05:41:09.000Z", 
        "hightempinsulin": 0.7, 
        "bolussnooze": 0, 
        "iob": 0.287
      }, 
      {
        "netbasalinsulin": 0.55, 
        "activity": 0.0078, 
        "basaliob": 0.242, 
        "time": "2016-05-20T05:46:09.000Z", 
        "hightempinsulin": 0.7, 
        "bolussnooze": 0, 
        "iob": 0.247
      }, 
      {
        "netbasalinsulin": 0.6, 
        "activity": 0.0066, 
        "basaliob": 0.214, 
        "time": "2016-05-20T05:51:09.000Z", 
        "hightempinsulin": 0.7, 
        "bolussnooze": 0, 
        "iob": 0.214
      }, 
      {
        "netbasalinsulin": 0.7, 
        "activity": 0.0054, 
        "basaliob": 0.187, 
        "time": "2016-05-20T05:56:09.000Z", 
        "hightempinsulin": 0.7, 
        "bolussnooze": 0, 
        "iob": 0.187
      }, 
      {
        "netbasalinsulin": 0.7, 
        "activity": 0.0049, 
        "basaliob": 0.163, 
        "time": "2016-05-20T06:01:09.000Z", 
        "hightempinsulin": 0.7, 
        "bolussnooze": 0, 
        "iob": 0.163
      }, 
      {
        "netbasalinsulin": 0.7, 
        "activity": 0.0045, 
        "basaliob": 0.14, 
        "time": "2016-05-20T06:06:09.000Z", 
        "hightempinsulin": 0.7, 
        "bolussnooze": 0, 
        "iob": 0.14
      }, 
      {
        "netbasalinsulin": 0.7, 
        "activity": 0.0042, 
        "basaliob": 0.12, 
        "time": "2016-05-20T06:11:09.000Z", 
        "hightempinsulin": 0.7, 
        "bolussnooze": 0, 
        "iob": 0.12
      }, 
      {
        "netbasalinsulin": 0.7, 
        "activity": 0.0038, 
        "basaliob": 0.101, 
        "time": "2016-05-20T06:16:09.000Z", 
        "hightempinsulin": 0.7, 
        "bolussnooze": 0, 
        "iob": 0.101
      }, 
      {
        "netbasalinsulin": 0.7, 
        "activity": 0.0034, 
        "basaliob": 0.084, 
        "time": "2016-05-20T06:21:09.000Z", 
        "hightempinsulin": 0.7, 
        "bolussnooze": 0, 
        "iob": 0.084
      }, 
      {
        "netbasalinsulin": 0.7, 
        "activity": 0.003, 
        "basaliob": 0.068, 
        "time": "2016-05-20T06:26:09.000Z", 
        "hightempinsulin": 0.7, 
        "bolussnooze": 0, 
        "iob": 0.068
      }, 
      {
        "netbasalinsulin": 0.65, 
        "activity": 0.0027, 
        "basaliob": 0.055, 
        "time": "2016-05-20T06:31:09.000Z", 
        "hightempinsulin": 0.65, 
        "bolussnooze": 0, 
        "iob": 0.055
      }, 
      {
        "netbasalinsulin": 0.65, 
        "activity": 0.0023, 
        "basaliob": 0.043, 
        "time": "2016-05-20T06:36:09.000Z", 
        "hightempinsulin": 0.65, 
        "bolussnooze": 0, 
        "iob": 0.043
      }, 
      {
        "netbasalinsulin": 0.6, 
        "activity": 0.002, 
        "basaliob": 0.033, 
        "time": "2016-05-20T06:41:09.000Z", 
        "hightempinsulin": 0.6, 
        "bolussnooze": 0, 
        "iob": 0.033
      }, 
      {
        "netbasalinsulin": 0.6, 
        "activity": 0.0017, 
        "basaliob": 0.025, 
        "time": "2016-05-20T06:46:09.000Z", 
        "hightempinsulin": 0.6, 
        "bolussnooze": 0, 
        "iob": 0.025
      }, 
      {
        "netbasalinsulin": 0.55, 
        "activity": 0.0014, 
        "basaliob": 0.018, 
        "time": "2016-05-20T06:51:09.000Z", 
        "hightempinsulin": 0.55, 
        "bolussnooze": 0, 
        "iob": 0.018
      }, 
      {
        "netbasalinsulin": 0.5, 
        "activity": 0.0011, 
        "basaliob": 0.012, 
        "time": "2016-05-20T06:56:09.000Z", 
        "hightempinsulin": 0.5, 
        "bolussnooze": 0, 
        "iob": 0.012
      }, 
      {
        "netbasalinsulin": 0.45, 
        "activity": 0.0008, 
        "basaliob": 0.008, 
        "time": "2016-05-20T07:01:09.000Z", 
        "hightempinsulin": 0.45, 
        "bolussnooze": 0, 
        "iob": 0.008
      }, 
      {
        "netbasalinsulin": 0.4, 
        "activity": 0.0006, 
        "basaliob": 0.005, 
        "time": "2016-05-20T07:06:09.000Z", 
        "hightempinsulin": 0.4, 
        "bolussnooze": 0, 
        "iob": 0.005
      }
    ], 
    "enacted": {
      "bg": 180, 
      "temp": "absolute", 
      "snoozeBG": 158, 
      "recieved": true, 
      "predBGs": {
        "COB": [
          180, 
          183, 
          186, 
          188, 
          190, 
          192, 
          193, 
          194, 
          195, 
          195, 
          195, 
          194, 
          194, 
          192, 
          191, 
          189, 
          187, 
          185, 
          183, 
          180, 
          178, 
          175, 
          173, 
          171, 
          169, 
          167, 
          166, 
          165, 
          163, 
          162, 
          161, 
          161, 
          160, 
          159, 
          159, 
          159, 
          158
        ], 
        "aCOB": [
          180, 
          182, 
          183, 
          184, 
          185, 
          186, 
          187, 
          187, 
          187, 
          187, 
          187, 
          187, 
          186, 
          185, 
          184, 
          183, 
          182, 
          180, 
          179, 
          177, 
          176, 
          175, 
          173, 
          172, 
          170, 
          168, 
          167, 
          165, 
          164, 
          163, 
          162, 
          161, 
          161, 
          160, 
          160, 
          159
        ], 
        "IOB": [
          180, 
          183, 
          184, 
          186, 
          186, 
          186, 
          184, 
          183, 
          180, 
          177, 
          172, 
          167, 
          162, 
          156, 
          151, 
          146, 
          142, 
          137, 
          133, 
          130, 
          127, 
          124, 
          122, 
          120, 
          118, 
          116, 
          115, 
          114, 
          112, 
          111, 
          110, 
          110, 
          109, 
          108, 
          108, 
          108, 
          107
        ]
      }, 
      "reason": "COB: 24, Dev: 69, BGI: -7.88, ISF: 80, Target: 115; Eventual BG 158>=115, temp 1.35<1.775U/hr", 
      "rate": 1.75, 
      "eventualBG": 158, 
      "timestamp": "2016-05-20T04:13:09.000Z", 
      "duration": 30, 
      "tick": "+6"
    }
  }, 
  "mmtune": {
    "scanDetails": [
      [
        "916.580", 
        5, 
        -45
      ], 
      [
        "916.600", 
        5, 
        -43
      ], 
      [
        "916.620", 
        5, 
        -42
      ], 
      [
        "916.640", 
        5, 
        -43
      ], 
      [
        "916.660", 
        5, 
        -43
      ], 
      [
        "916.680", 
        5, 
        -43
      ], 
      [
        "916.700", 
        5, 
        -45
      ], 
      [
        "916.720", 
        5, 
        -54
      ]
    ], 
    "setFreq": 916.62, 
    "timestamp": "2016-05-20T04:11:23.000Z", 
    "usedDefault": false
  }
}