{
  "device": "openaps://indy-e3", 
  "pump": {
    "battery": {
      "status": "normal", 
      "voltage": 1.41
    }, 
    "status": {
      "status": "normal", 
      "timestamp": "2016-05-25T19:37:25.000Z", 
      "bolusing": false, 
      "suspended": false
    }, 
    "reservoir": 51.325, 
    "clock": "2016-05-25T12:36:52-07:00"
  }, 
  "openaps": {
    "suggested": {
      "bg": 82, 
      "temp": "absolute", 
      "snoozeBG": 86, 
      "timestamp": "2016-05-25T19:38:30.000Z", 
      "predBGs": {
        "COB": [
          82, 
          83, 
          83, 
          83, 
          83, 
          84, 
          86, 
          88, 
          90, 
          92, 
          95, 
          98, 
          101, 
          104, 
          107, 
          111, 
          115, 
          119, 
          123, 
          127, 
          132, 
          136, 
          141, 
          145, 
          149, 
          154, 
          157, 
          161, 
          164, 
          166, 
          169, 
          170, 
          172, 
          173, 
          174, 
          175
        ], 
        "aCOB": [
          82, 
          81, 
          80, 
          79, 
          78, 
          78, 
          78, 
          79, 
          80, 
          82, 
          84, 
          86, 
          89, 
          91, 
          94, 
          98, 
          101, 
          105, 
          109, 
          113, 
          118, 
          122, 
          127, 
          131, 
          136, 
          141, 
          145, 
          149, 
          152, 
          156, 
          159, 
          161, 
          164, 
          166, 
          168, 
          170, 
          172
        ], 
        "IOB": [
          82, 
          82, 
          81, 
          79, 
          77, 
          75, 
          72, 
          70, 
          66, 
          63, 
          59, 
          55, 
          50, 
          46, 
          42, 
          39
        ]
      }, 
      "reason": "COB: 48, Dev: 69, BGI: -10.52, ISF: 80, Target: 115; BG 82<82.5, avg delta 1.00>0, temp 0.5 ~ req 0.5U/hr", 
      "eventualBG": 175, 
      "tick": "+1"
    }, 
    "iob": [
      {
        "netbasalinsulin": 0.85, 
        "activity": 0.0263, 
        "basaliob": 0.292, 
        "time": "2016-05-25T19:36:52.000Z", 
        "hightempinsulin": 1.25, 
        "bolussnooze": 0, 
        "iob": 1.296
      }, 
      {
        "netbasalinsulin": 0.9, 
        "activity": 0.0266, 
        "basaliob": 0.247, 
        "time": "2016-05-25T19:41:52.000Z", 
        "hightempinsulin": 1.25, 
        "bolussnooze": 0, 
        "iob": 1.163
      }, 
      {
        "netbasalinsulin": 0.9, 
        "activity": 0.0263, 
        "basaliob": 0.204, 
        "time": "2016-05-25T19:46:52.000Z", 
        "hightempinsulin": 1.25, 
        "bolussnooze": 0, 
        "iob": 1.031
      }, 
      {
        "netbasalinsulin": 0.9, 
        "activity": 0.0244, 
        "basaliob": 0.165, 
        "time": "2016-05-25T19:51:52.000Z", 
        "hightempinsulin": 1.25, 
        "bolussnooze": 0, 
        "iob": 0.909
      }, 
      {
        "netbasalinsulin": 0.95, 
        "activity": 0.0224, 
        "basaliob": 0.13, 
        "time": "2016-05-25T19:56:52.000Z", 
        "hightempinsulin": 1.25, 
        "bolussnooze": 0, 
        "iob": 0.797
      }, 
      {
        "netbasalinsulin": 0.95, 
        "activity": 0.0205, 
        "basaliob": 0.098, 
        "time": "2016-05-25T20:01:52.000Z", 
        "hightempinsulin": 1.25, 
        "bolussnooze": 0, 
        "iob": 0.694
      }, 
      {
        "netbasalinsulin": 0.9, 
        "activity": 0.0189, 
        "basaliob": 0.071, 
        "time": "2016-05-25T20:06:52.000Z", 
        "hightempinsulin": 1.2, 
        "bolussnooze": 0, 
        "iob": 0.6
      }, 
      {
        "netbasalinsulin": 0.85, 
        "activity": 0.0174, 
        "basaliob": 0.046, 
        "time": "2016-05-25T20:11:52.000Z", 
        "hightempinsulin": 1.15, 
        "bolussnooze": 0, 
        "iob": 0.513
      }, 
      {
        "netbasalinsulin": 0.85, 
        "activity": 0.0159, 
        "basaliob": 0.026, 
        "time": "2016-05-25T20:16:52.000Z", 
        "hightempinsulin": 1.15, 
        "bolussnooze": 0, 
        "iob": 0.433
      }, 
      {
        "netbasalinsulin": 0.8, 
        "activity": 0.0145, 
        "basaliob": 0.008, 
        "time": "2016-05-25T20:21:52.000Z", 
        "hightempinsulin": 1.1, 
        "bolussnooze": 0, 
        "iob": 0.361
      }, 
      {
        "netbasalinsulin": 0.8, 
        "activity": 0.0131, 
        "basaliob": -0.006, 
        "time": "2016-05-25T20:26:52.000Z", 
        "hightempinsulin": 1.1, 
        "bolussnooze": 0, 
        "iob": 0.296
      }, 
      {
        "netbasalinsulin": 0.9, 
        "activity": 0.0117, 
        "basaliob": -0.018, 
        "time": "2016-05-25T20:31:52.000Z", 
        "hightempinsulin": 1.1, 
        "bolussnooze": 0, 
        "iob": 0.237
      }, 
      {
        "netbasalinsulin": 0.9, 
        "activity": 0.0104, 
        "basaliob": -0.027, 
        "time": "2016-05-25T20:36:52.000Z", 
        "hightempinsulin": 1.1, 
        "bolussnooze": 0, 
        "iob": 0.185
      }, 
      {
        "netbasalinsulin": 0.85, 
        "activity": 0.0091, 
        "basaliob": -0.033, 
        "time": "2016-05-25T20:41:52.000Z", 
        "hightempinsulin": 1.05, 
        "bolussnooze": 0, 
        "iob": 0.14
      }, 
      {
        "netbasalinsulin": 0.8, 
        "activity": 0.0079, 
        "basaliob": -0.037, 
        "time": "2016-05-25T20:46:52.000Z", 
        "hightempinsulin": 1, 
        "bolussnooze": 0, 
        "iob": 0.1
      }, 
      {
        "netbasalinsulin": 0.7, 
        "activity": 0.0067, 
        "basaliob": -0.04, 
        "time": "2016-05-25T20:51:52.000Z", 
        "hightempinsulin": 0.9, 
        "bolussnooze": 0, 
        "iob": 0.067
      }, 
      {
        "netbasalinsulin": 0.65, 
        "activity": 0.0055, 
        "basaliob": -0.04, 
        "time": "2016-05-25T20:56:52.000Z", 
        "hightempinsulin": 0.85, 
        "bolussnooze": 0, 
        "iob": 0.039
      }, 
      {
        "netbasalinsulin": 0.5, 
        "activity": 0.0044, 
        "basaliob": -0.039, 
        "time": "2016-05-25T21:01:52.000Z", 
        "hightempinsulin": 0.7, 
        "bolussnooze": 0, 
        "iob": 0.017
      }, 
      {
        "netbasalinsulin": 0.4, 
        "activity": 0.0034, 
        "basaliob": -0.037, 
        "time": "2016-05-25T21:06:52.000Z", 
        "hightempinsulin": 0.6, 
        "bolussnooze": 0, 
        "iob": 0
      }, 
      {
        "netbasalinsulin": 0.35, 
        "activity": 0.0024, 
        "basaliob": -0.033, 
        "time": "2016-05-25T21:11:52.000Z", 
        "hightempinsulin": 0.55, 
        "bolussnooze": 0, 
        "iob": -0.012
      }, 
      {
        "netbasalinsulin": 0.2, 
        "activity": 0.0015, 
        "basaliob": -0.029, 
        "time": "2016-05-25T21:16:52.000Z", 
        "hightempinsulin": 0.4, 
        "bolussnooze": 0, 
        "iob": -0.019
      }, 
      {
        "netbasalinsulin": 0.1, 
        "activity": 0.0006, 
        "basaliob": -0.025, 
        "time": "2016-05-25T21:21:52.000Z", 
        "hightempinsulin": 0.3, 
        "bolussnooze": 0, 
        "iob": -0.022
      }, 
      {
        "netbasalinsulin": -0.05, 
        "activity": -0.0002, 
        "basaliob": -0.02, 
        "time": "2016-05-25T21:26:52.000Z", 
        "hightempinsulin": 0.15, 
        "bolussnooze": 0, 
        "iob": -0.021
      }, 
      {
        "netbasalinsulin": -0.15, 
        "activity": -0.0008, 
        "basaliob": -0.016, 
        "time": "2016-05-25T21:31:52.000Z", 
        "hightempinsulin": 0.05, 
        "bolussnooze": 0, 
        "iob": -0.016
      }, 
      {
        "netbasalinsulin": -0.15, 
        "activity": -0.0008, 
        "basaliob": -0.012, 
        "time": "2016-05-25T21:36:52.000Z", 
        "hightempinsulin": 0.05, 
        "bolussnooze": 0, 
        "iob": -0.012
      }, 
      {
        "netbasalinsulin": -0.2, 
        "activity": -0.0007, 
        "basaliob": -0.009, 
        "time": "2016-05-25T21:41:52.000Z", 
        "hightempinsulin": 0, 
        "bolussnooze": 0, 
        "iob": -0.009
      }, 
      {
        "netbasalinsulin": -0.2, 
        "activity": -0.0006, 
        "basaliob": -0.006, 
        "time": "2016-05-25T21:46:52.000Z", 
        "hightempinsulin": 0, 
        "bolussnooze": 0, 
        "iob": -0.006
      }, 
      {
        "netbasalinsulin": -0.2, 
        "activity": -0.0004, 
        "basaliob": -0.004, 
        "time": "2016-05-25T21:51:52.000Z", 
        "hightempinsulin": 0, 
        "bolussnooze": 0, 
        "iob": -0.004
      }, 
      {
        "netbasalinsulin": -0.2, 
        "activity": -0.0003, 
        "basaliob": -0.002, 
        "time": "2016-05-25T21:56:52.000Z", 
        "hightempinsulin": 0, 
        "bolussnooze": 0, 
        "iob": -0.002
      }, 
      {
        "netbasalinsulin": -0.2, 
        "activity": -0.0002, 
        "basaliob": -0.001, 
        "time": "2016-05-25T22:01:52.000Z", 
        "hightempinsulin": 0, 
        "bolussnooze": 0, 
        "iob": -0.001
      }, 
      {
        "netbasalinsulin": -0.15, 
        "activity": -0.0001, 
        "basaliob": -0.001, 
        "time": "2016-05-25T22:06:52.000Z", 
        "hightempinsulin": 0, 
        "bolussnooze": 0, 
        "iob": -0.001
      }, 
      {
        "netbasalinsulin": -0.1, 
        "activity": -0.0001, 
        "basaliob": 0, 
        "time": "2016-05-25T22:11:52.000Z", 
        "hightempinsulin": 0, 
        "bolussnooze": 0, 
        "iob": 0
      }, 
      {
        "netbasalinsulin": -0.05, 
        "activity": 0, 
        "basaliob": 0, 
        "time": "2016-05-25T22:16:52.000Z", 
        "hightempinsulin": 0, 
        "bolussnooze": 0, 
        "iob": 0
      }, 
      {
        "netbasalinsulin": -0.05, 
        "activity": 0, 
        "basaliob": 0, 
        "time": "2016-05-25T22:21:52.000Z", 
        "hightempinsulin": 0, 
        "bolussnooze": 0, 
        "iob": 0
      }, 
      {
        "netbasalinsulin": 0, 
        "activity": 0, 
        "basaliob": 0, 
        "time": "2016-05-25T22:26:52.000Z", 
        "hightempinsulin": 0, 
        "bolussnooze": 0, 
        "iob": 0
      }, 
      {
        "netbasalinsulin": 0, 
        "activity": 0, 
        "basaliob": 0, 
        "time": "2016-05-25T22:31:52.000Z", 
        "hightempinsulin": 0, 
        "bolussnooze": 0, 
        "iob": 0
      }
    ], 
    "enacted": {
      "bg": 78, 
      "temp": "absolute", 
      "snoozeBG": 51, 
      "recieved": true, 
      "predBGs": {
        "COB": [
          78, 
          75, 
          72, 
          68, 
          64, 
          60, 
          57, 
          55, 
          53, 
          52, 
          51, 
          51, 
          52, 
          53, 
          54, 
          56, 
          58, 
          61, 
          64, 
          67, 
          71, 
          74, 
          79, 
          83, 
          87, 
          92, 
          97, 
          101, 
          106, 
          110, 
          114, 
          118, 
          121, 
          125, 
          128, 
          131, 
          134
        ], 
        "aCOB": [
          78, 
          78, 
          77, 
          76, 
          74, 
          73, 
          72, 
          71, 
          71, 
          72, 
          73, 
          75, 
          76, 
          79, 
          81, 
          84, 
          87, 
          91, 
          95, 
          99, 
          103, 
          107, 
          112, 
          116, 
          121, 
          125, 
          130, 
          134, 
          138, 
          142, 
          146, 
          149, 
          151, 
          154, 
          156, 
          158, 
          160
        ], 
        "IOB": [
          78, 
          74, 
          70, 
          65, 
          59, 
          53, 
          47, 
          41, 
          39, 
          39, 
          39, 
          39, 
          39
        ]
      }, 
      "reason": "COB: 48, Dev: 43, BGI: -10.16, ISF: 80, Target: 115; BG 78<82.5, delta 1>0; setting current basal of 0.5 as temp", 
      "rate": 0.5, 
      "eventualBG": 134, 
      "timestamp": "2016-05-25T19:29:02.000Z", 
      "duration": 30, 
      "tick": "+1"
    }
  }, 
  "mmtune": {
    "scanDetails": [
      [
        "916.560", 
        2, 
        -94
      ], 
      [
        "916.580", 
        4, 
        -88
      ], 
      [
        "916.600", 
        5, 
        -81
      ], 
      [
        "916.620", 
        5, 
        -83
      ], 
      [
        "916.640", 
        3, 
        -89
      ], 
      [
        "916.660", 
        5, 
        -88
      ], 
      [
        "916.680", 
        3, 
        -94
      ]
    ], 
    "setFreq": 916.6, 
    "timestamp": "2016-05-25T19:37:07.000Z", 
    "usedDefault": false
  }
}