{
  "device": "openaps://indy-e3", 
  "pump": {
    "battery": {
      "status": "normal", 
      "voltage": 1.36
    }, 
    "status": {
      "status": "normal", 
      "timestamp": "2016-05-20T17:26:44.000Z", 
      "bolusing": false, 
      "suspended": false
    }, 
    "reservoir": 174.2, 
    "clock": "2016-05-20T10:26:09-07:00"
  }, 
  "openaps": {
    "suggested": {
      "bg": 87, 
      "temp": "absolute", 
      "snoozeBG": -15, 
      "timestamp": "2016-05-20T17:27:59.000Z", 
      "predBGs": {
        "aCOB": [
          87, 
          86, 
          85, 
          85, 
          84, 
          83, 
          82, 
          82, 
          81, 
          81, 
          81, 
          81, 
          83, 
          84, 
          85, 
          85, 
          86, 
          86, 
          86, 
          86, 
          85, 
          84, 
          84, 
          83, 
          83, 
          83, 
          83, 
          83, 
          84, 
          84, 
          85, 
          85, 
          86, 
          86, 
          86, 
          87
        ], 
        "IOB": [
          87, 
          77, 
          67, 
          58, 
          49, 
          41, 
          39, 
          39, 
          39, 
          39, 
          39, 
          39, 
          39
        ]
      }, 
      "reason": "COB: 26, Dev: -50, BGI: -2.68, ISF: 69.6, Target: 115; Eventual BG -27<115, setting -6.811U/hr, but 29m left and 0 ~ req 0U/hr: no action required", 
      "eventualBG": -27, 
      "tick": -10
    }, 
    "iob": [
      {
        "netbasalinsulin": 0.15, 
        "activity": 0.0077, 
        "basaliob": 0.018, 
        "time": "2016-05-20T17:26:09.000Z", 
        "hightempinsulin": 0.75, 
        "bolussnooze": 0.115, 
        "iob": 0.926
      }, 
      {
        "netbasalinsulin": 0.15, 
        "activity": 0.0083, 
        "basaliob": -0.046, 
        "time": "2016-05-20T17:31:09.000Z", 
        "hightempinsulin": 0.75, 
        "bolussnooze": 0.037, 
        "iob": 0.835
      }, 
      {
        "netbasalinsulin": 0.15, 
        "activity": 0.0088, 
        "basaliob": -0.108, 
        "time": "2016-05-20T17:36:09.000Z", 
        "hightempinsulin": 0.75, 
        "bolussnooze": 0.002, 
        "iob": 0.741
      }, 
      {
        "netbasalinsulin": 0.15, 
        "activity": 0.0094, 
        "basaliob": -0.17, 
        "time": "2016-05-20T17:41:09.000Z", 
        "hightempinsulin": 0.75, 
        "bolussnooze": 0, 
        "iob": 0.644
      }, 
      {
        "netbasalinsulin": 0.1, 
        "activity": 0.0099, 
        "basaliob": -0.23, 
        "time": "2016-05-20T17:46:09.000Z", 
        "hightempinsulin": 0.75, 
        "bolussnooze": 0, 
        "iob": 0.544
      }, 
      {
        "netbasalinsulin": 0.1, 
        "activity": 0.0103, 
        "basaliob": -0.289, 
        "time": "2016-05-20T17:51:09.000Z", 
        "hightempinsulin": 0.75, 
        "bolussnooze": 0, 
        "iob": 0.443
      }, 
      {
        "netbasalinsulin": 0.15, 
        "activity": 0.0106, 
        "basaliob": -0.296, 
        "time": "2016-05-20T17:56:09.000Z", 
        "hightempinsulin": 0.75, 
        "bolussnooze": 0, 
        "iob": 0.39
      }, 
      {
        "netbasalinsulin": 0.15, 
        "activity": 0.0108, 
        "basaliob": -0.3, 
        "time": "2016-05-20T18:01:09.000Z", 
        "hightempinsulin": 0.75, 
        "bolussnooze": 0, 
        "iob": 0.335
      }, 
      {
        "netbasalinsulin": 0.15, 
        "activity": 0.011, 
        "basaliob": -0.301, 
        "time": "2016-05-20T18:06:09.000Z", 
        "hightempinsulin": 0.75, 
        "bolussnooze": 0, 
        "iob": 0.28
      }, 
      {
        "netbasalinsulin": 0.15, 
        "activity": 0.0104, 
        "basaliob": -0.299, 
        "time": "2016-05-20T18:11:09.000Z", 
        "hightempinsulin": 0.75, 
        "bolussnooze": 0, 
        "iob": 0.227
      }, 
      {
        "netbasalinsulin": 0.1, 
        "activity": 0.0093, 
        "basaliob": -0.294, 
        "time": "2016-05-20T18:16:09.000Z", 
        "hightempinsulin": 0.7, 
        "bolussnooze": 0, 
        "iob": 0.181
      }, 
      {
        "netbasalinsulin": 0, 
        "activity": 0.0081, 
        "basaliob": -0.286, 
        "time": "2016-05-20T18:21:09.000Z", 
        "hightempinsulin": 0.6, 
        "bolussnooze": 0, 
        "iob": 0.14
      }, 
      {
        "netbasalinsulin": -0.1, 
        "activity": 0.0071, 
        "basaliob": -0.275, 
        "time": "2016-05-20T18:26:09.000Z", 
        "hightempinsulin": 0.5, 
        "bolussnooze": 0, 
        "iob": 0.105
      }, 
      {
        "netbasalinsulin": -0.2, 
        "activity": 0.0061, 
        "basaliob": -0.262, 
        "time": "2016-05-20T18:31:09.000Z", 
        "hightempinsulin": 0.4, 
        "bolussnooze": 0, 
        "iob": 0.075
      }, 
      {
        "netbasalinsulin": -0.25, 
        "activity": 0.0052, 
        "basaliob": -0.247, 
        "time": "2016-05-20T18:36:09.000Z", 
        "hightempinsulin": 0.35, 
        "bolussnooze": 0, 
        "iob": 0.049
      }, 
      {
        "netbasalinsulin": -0.25, 
        "activity": 0.0045, 
        "basaliob": -0.231, 
        "time": "2016-05-20T18:41:09.000Z", 
        "hightempinsulin": 0.35, 
        "bolussnooze": 0, 
        "iob": 0.026
      }, 
      {
        "netbasalinsulin": -0.25, 
        "activity": 0.0038, 
        "basaliob": -0.214, 
        "time": "2016-05-20T18:46:09.000Z", 
        "hightempinsulin": 0.35, 
        "bolussnooze": 0, 
        "iob": 0.007
      }, 
      {
        "netbasalinsulin": -0.3, 
        "activity": 0.0032, 
        "basaliob": -0.197, 
        "time": "2016-05-20T18:51:09.000Z", 
        "hightempinsulin": 0.3, 
        "bolussnooze": 0, 
        "iob": -0.009
      }, 
      {
        "netbasalinsulin": -0.3, 
        "activity": 0.0026, 
        "basaliob": -0.18, 
        "time": "2016-05-20T18:56:09.000Z", 
        "hightempinsulin": 0.3, 
        "bolussnooze": 0, 
        "iob": -0.022
      }, 
      {
        "netbasalinsulin": -0.35, 
        "activity": 0.0022, 
        "basaliob": -0.163, 
        "time": "2016-05-20T19:01:09.000Z", 
        "hightempinsulin": 0.25, 
        "bolussnooze": 0, 
        "iob": -0.032
      }, 
      {
        "netbasalinsulin": -0.35, 
        "activity": 0.0018, 
        "basaliob": -0.147, 
        "time": "2016-05-20T19:06:09.000Z", 
        "hightempinsulin": 0.25, 
        "bolussnooze": 0, 
        "iob": -0.041
      }, 
      {
        "netbasalinsulin": -0.35, 
        "activity": 0.0014, 
        "basaliob": -0.132, 
        "time": "2016-05-20T19:11:09.000Z", 
        "hightempinsulin": 0.25, 
        "bolussnooze": 0, 
        "iob": -0.048
      }, 
      {
        "netbasalinsulin": -0.3, 
        "activity": 0.0011, 
        "basaliob": -0.117, 
        "time": "2016-05-20T19:16:09.000Z", 
        "hightempinsulin": 0.25, 
        "bolussnooze": 0, 
        "iob": -0.054
      }, 
      {
        "netbasalinsulin": -0.25, 
        "activity": 0.0007, 
        "basaliob": -0.104, 
        "time": "2016-05-20T19:21:09.000Z", 
        "hightempinsulin": 0.25, 
        "bolussnooze": 0, 
        "iob": -0.057
      }, 
      {
        "netbasalinsulin": -0.2, 
        "activity": 0.0003, 
        "basaliob": -0.091, 
        "time": "2016-05-20T19:26:09.000Z", 
        "hightempinsulin": 0.25, 
        "bolussnooze": 0, 
        "iob": -0.058
      }, 
      {
        "netbasalinsulin": -0.2, 
        "activity": -0.0002, 
        "basaliob": -0.078, 
        "time": "2016-05-20T19:31:09.000Z", 
        "hightempinsulin": 0.25, 
        "bolussnooze": 0, 
        "iob": -0.058
      }, 
      {
        "netbasalinsulin": -0.25, 
        "activity": -0.0006, 
        "basaliob": -0.066, 
        "time": "2016-05-20T19:36:09.000Z", 
        "hightempinsulin": 0.2, 
        "bolussnooze": 0, 
        "iob": -0.055
      }, 
      {
        "netbasalinsulin": -0.3, 
        "activity": -0.0009, 
        "basaliob": -0.055, 
        "time": "2016-05-20T19:41:09.000Z", 
        "hightempinsulin": 0.15, 
        "bolussnooze": 0, 
        "iob": -0.05
      }, 
      {
        "netbasalinsulin": -0.35, 
        "activity": -0.0013, 
        "basaliob": -0.045, 
        "time": "2016-05-20T19:46:09.000Z", 
        "hightempinsulin": 0.1, 
        "bolussnooze": 0, 
        "iob": -0.044
      }, 
      {
        "netbasalinsulin": -0.4, 
        "activity": -0.0016, 
        "basaliob": -0.035, 
        "time": "2016-05-20T19:51:09.000Z", 
        "hightempinsulin": 0.05, 
        "bolussnooze": 0, 
        "iob": -0.035
      }, 
      {
        "netbasalinsulin": -0.45, 
        "activity": -0.0016, 
        "basaliob": -0.027, 
        "time": "2016-05-20T19:56:09.000Z", 
        "hightempinsulin": 0, 
        "bolussnooze": 0, 
        "iob": -0.027
      }, 
      {
        "netbasalinsulin": -0.45, 
        "activity": -0.0014, 
        "basaliob": -0.02, 
        "time": "2016-05-20T20:01:09.000Z", 
        "hightempinsulin": 0, 
        "bolussnooze": 0, 
        "iob": -0.02
      }, 
      {
        "netbasalinsulin": -0.45, 
        "activity": -0.0011, 
        "basaliob": -0.015, 
        "time": "2016-05-20T20:06:09.000Z", 
        "hightempinsulin": 0, 
        "bolussnooze": 0, 
        "iob": -0.015
      }, 
      {
        "netbasalinsulin": -0.45, 
        "activity": -0.0009, 
        "basaliob": -0.01, 
        "time": "2016-05-20T20:11:09.000Z", 
        "hightempinsulin": 0, 
        "bolussnooze": 0, 
        "iob": -0.01
      }, 
      {
        "netbasalinsulin": -0.35, 
        "activity": -0.0007, 
        "basaliob": -0.007, 
        "time": "2016-05-20T20:16:09.000Z", 
        "hightempinsulin": 0, 
        "bolussnooze": 0, 
        "iob": -0.007
      }, 
      {
        "netbasalinsulin": -0.3, 
        "activity": -0.0005, 
        "basaliob": -0.004, 
        "time": "2016-05-20T20:21:09.000Z", 
        "hightempinsulin": 0, 
        "bolussnooze": 0, 
        "iob": -0.004
      }
    ], 
    "enacted": {
      "bg": 97, 
      "temp": "absolute", 
      "snoozeBG": 7, 
      "recieved": true, 
      "predBGs": {
        "aCOB": [
          97, 
          95, 
          94, 
          92, 
          91, 
          89, 
          88, 
          87, 
          86, 
          85, 
          85, 
          85, 
          85, 
          86, 
          86, 
          87, 
          86, 
          86, 
          85, 
          84, 
          83, 
          82, 
          81, 
          80, 
          79, 
          79, 
          78, 
          78, 
          78, 
          78, 
          78, 
          78, 
          79
        ], 
        "IOB": [
          97, 
          86, 
          75, 
          65, 
          56, 
          47, 
          39, 
          39, 
          39, 
          39, 
          39, 
          39, 
          39
        ]
      }, 
      "reason": "COB: 26, Dev: -39, BGI: -2.58, ISF: 69.6, Target: 115; Eventual BG -11<115, setting -5.547U/hr", 
      "rate": 0, 
      "eventualBG": -11, 
      "timestamp": "2016-05-20T17:25:11.000Z", 
      "duration": 30, 
      "tick": -12
    }
  }, 
  "mmtune": {
    "scanDetails": [
      [
        "916.560", 
        5, 
        -75
      ], 
      [
        "916.580", 
        5, 
        -72
      ], 
      [
        "916.600", 
        5, 
        -71
      ], 
      [
        "916.620", 
        5, 
        -71
      ], 
      [
        "916.640", 
        5, 
        -68
      ], 
      [
        "916.660", 
        5, 
        -70
      ], 
      [
        "916.680", 
        5, 
        -72
      ], 
      [
        "916.700", 
        5, 
        -82
      ]
    ], 
    "setFreq": 916.64, 
    "timestamp": "2016-05-20T17:26:23.000Z", 
    "usedDefault": false
  }
}