{
  "device": "openaps://indy-e3", 
  "pump": {
    "battery": {
      "status": "normal", 
      "voltage": 1.45
    }, 
    "status": {
      "status": "normal", 
      "timestamp": "2016-05-07T00:53:44.000Z", 
      "bolusing": false, 
      "suspended": false
    }, 
    "reservoir": 106.05, 
    "clock": "2016-05-06T17:53:04-07:00"
  }, 
  "openaps": {
    "suggested": {
      "bg": 154, 
      "temp": "absolute", 
      "snoozeBG": 92, 
      "timestamp": "2016-05-07T00:55:01.000Z", 
      "predBGs": {
        "aCOB": [
          154, 
          155, 
          156, 
          157, 
          157, 
          157, 
          156, 
          156, 
          155, 
          153, 
          152, 
          151, 
          149, 
          148, 
          145, 
          143, 
          140, 
          137, 
          135, 
          132, 
          129, 
          126, 
          124, 
          121, 
          118, 
          115, 
          113, 
          110, 
          109, 
          107, 
          106, 
          105, 
          104, 
          103
        ], 
        "IOB": [
          154, 
          146, 
          138, 
          129, 
          121, 
          113, 
          105, 
          97, 
          89, 
          81, 
          74, 
          67, 
          61, 
          54, 
          47, 
          41, 
          39
        ]
      }, 
      "rate": 0.5, 
      "reason": "COB: 25, Dev: -1, BGI: -2.76, Target: 80; Eventual BG 21<80, bolus snooze: eventual BG range 21-92; setting current basal of 0.5 as temp", 
      "eventualBG": 21, 
      "duration": 30, 
      "tick": -9
    }, 
    "iob": [
      {
        "netbasalinsulin": 1, 
        "activity": 0.0069, 
        "basaliob": 1.049, 
        "time": "2016-05-07T00:53:04.000Z", 
        "hightempinsulin": 1.25, 
        "bolussnooze": 0.594, 
        "iob": 1.649
      }, 
      {
        "netbasalinsulin": 1, 
        "activity": 0.008, 
        "basaliob": 1.014, 
        "time": "2016-05-07T00:58:04.000Z", 
        "hightempinsulin": 1.25, 
        "bolussnooze": 0.567, 
        "iob": 1.609
      }, 
      {
        "netbasalinsulin": 1, 
        "activity": 0.0092, 
        "basaliob": 0.973, 
        "time": "2016-05-07T01:03:04.000Z", 
        "hightempinsulin": 1.25, 
        "bolussnooze": 0.521, 
        "iob": 1.563
      }, 
      {
        "netbasalinsulin": 1.05, 
        "activity": 0.0105, 
        "basaliob": 0.979, 
        "time": "2016-05-07T01:08:04.000Z", 
        "hightempinsulin": 1.3, 
        "bolussnooze": 0.455, 
        "iob": 1.56
      }, 
      {
        "netbasalinsulin": 1.1, 
        "activity": 0.0117, 
        "basaliob": 0.931, 
        "time": "2016-05-07T01:13:04.000Z", 
        "hightempinsulin": 1.3, 
        "bolussnooze": 0.368, 
        "iob": 1.501
      }, 
      {
        "netbasalinsulin": 1.15, 
        "activity": 0.0128, 
        "basaliob": 0.879, 
        "time": "2016-05-07T01:18:04.000Z", 
        "hightempinsulin": 1.3, 
        "bolussnooze": 0.273, 
        "iob": 1.437
      }, 
      {
        "netbasalinsulin": 1.2, 
        "activity": 0.0138, 
        "basaliob": 0.824, 
        "time": "2016-05-07T01:23:04.000Z", 
        "hightempinsulin": 1.3, 
        "bolussnooze": 0.192, 
        "iob": 1.368
      }, 
      {
        "netbasalinsulin": 1.25, 
        "activity": 0.0146, 
        "basaliob": 0.768, 
        "time": "2016-05-07T01:28:04.000Z", 
        "hightempinsulin": 1.3, 
        "bolussnooze": 0.125, 
        "iob": 1.295
      }, 
      {
        "netbasalinsulin": 1.25, 
        "activity": 0.0153, 
        "basaliob": 0.711, 
        "time": "2016-05-07T01:33:04.000Z", 
        "hightempinsulin": 1.3, 
        "bolussnooze": 0.072, 
        "iob": 1.218
      }, 
      {
        "netbasalinsulin": 1.3, 
        "activity": 0.0158, 
        "basaliob": 0.653, 
        "time": "2016-05-07T01:38:04.000Z", 
        "hightempinsulin": 1.3, 
        "bolussnooze": 0.034, 
        "iob": 1.139
      }, 
      {
        "netbasalinsulin": 1.3, 
        "activity": 0.0161, 
        "basaliob": 0.596, 
        "time": "2016-05-07T01:43:04.000Z", 
        "hightempinsulin": 1.3, 
        "bolussnooze": 0.01, 
        "iob": 1.059
      }, 
      {
        "netbasalinsulin": 1.3, 
        "activity": 0.0163, 
        "basaliob": 0.541, 
        "time": "2016-05-07T01:48:04.000Z", 
        "hightempinsulin": 1.3, 
        "bolussnooze": 0, 
        "iob": 0.977
      }, 
      {
        "netbasalinsulin": 1.3, 
        "activity": 0.0164, 
        "basaliob": 0.486, 
        "time": "2016-05-07T01:53:04.000Z", 
        "hightempinsulin": 1.3, 
        "bolussnooze": 0, 
        "iob": 0.895
      }, 
      {
        "netbasalinsulin": 1.3, 
        "activity": 0.0165, 
        "basaliob": 0.434, 
        "time": "2016-05-07T01:58:04.000Z", 
        "hightempinsulin": 1.3, 
        "bolussnooze": 0, 
        "iob": 0.812
      }, 
      {
        "netbasalinsulin": 1.3, 
        "activity": 0.0164, 
        "basaliob": 0.385, 
        "time": "2016-05-07T02:03:04.000Z", 
        "hightempinsulin": 1.3, 
        "bolussnooze": 0, 
        "iob": 0.73
      }, 
      {
        "netbasalinsulin": 1.3, 
        "activity": 0.0158, 
        "basaliob": 0.338, 
        "time": "2016-05-07T02:08:04.000Z", 
        "hightempinsulin": 1.3, 
        "bolussnooze": 0, 
        "iob": 0.651
      }, 
      {
        "netbasalinsulin": 1.3, 
        "activity": 0.0148, 
        "basaliob": 0.295, 
        "time": "2016-05-07T02:13:04.000Z", 
        "hightempinsulin": 1.3, 
        "bolussnooze": 0, 
        "iob": 0.576
      }, 
      {
        "netbasalinsulin": 1.3, 
        "activity": 0.0139, 
        "basaliob": 0.254, 
        "time": "2016-05-07T02:18:04.000Z", 
        "hightempinsulin": 1.3, 
        "bolussnooze": 0, 
        "iob": 0.507
      }, 
      {
        "netbasalinsulin": 1.3, 
        "activity": 0.0129, 
        "basaliob": 0.217, 
        "time": "2016-05-07T02:23:04.000Z", 
        "hightempinsulin": 1.3, 
        "bolussnooze": 0, 
        "iob": 0.442
      }, 
      {
        "netbasalinsulin": 1.3, 
        "activity": 0.0119, 
        "basaliob": 0.183, 
        "time": "2016-05-07T02:28:04.000Z", 
        "hightempinsulin": 1.3, 
        "bolussnooze": 0, 
        "iob": 0.383
      }, 
      {
        "netbasalinsulin": 1.3, 
        "activity": 0.0109, 
        "basaliob": 0.153, 
        "time": "2016-05-07T02:33:04.000Z", 
        "hightempinsulin": 1.3, 
        "bolussnooze": 0, 
        "iob": 0.328
      }, 
      {
        "netbasalinsulin": 1.2, 
        "activity": 0.0099, 
        "basaliob": 0.126, 
        "time": "2016-05-07T02:38:04.000Z", 
        "hightempinsulin": 1.2, 
        "bolussnooze": 0, 
        "iob": 0.278
      }, 
      {
        "netbasalinsulin": 1.2, 
        "activity": 0.009, 
        "basaliob": 0.102, 
        "time": "2016-05-07T02:43:04.000Z", 
        "hightempinsulin": 1.2, 
        "bolussnooze": 0, 
        "iob": 0.233
      }, 
      {
        "netbasalinsulin": 1.15, 
        "activity": 0.0081, 
        "basaliob": 0.082, 
        "time": "2016-05-07T02:48:04.000Z", 
        "hightempinsulin": 1.15, 
        "bolussnooze": 0, 
        "iob": 0.193
      }, 
      {
        "netbasalinsulin": 1.1, 
        "activity": 0.0072, 
        "basaliob": 0.064, 
        "time": "2016-05-07T02:53:04.000Z", 
        "hightempinsulin": 1.1, 
        "bolussnooze": 0, 
        "iob": 0.157
      }, 
      {
        "netbasalinsulin": 1.05, 
        "activity": 0.0063, 
        "basaliob": 0.049, 
        "time": "2016-05-07T02:58:04.000Z", 
        "hightempinsulin": 1.05, 
        "bolussnooze": 0, 
        "iob": 0.126
      }, 
      {
        "netbasalinsulin": 0.95, 
        "activity": 0.0054, 
        "basaliob": 0.037, 
        "time": "2016-05-07T03:03:04.000Z", 
        "hightempinsulin": 0.95, 
        "bolussnooze": 0, 
        "iob": 0.099
      }, 
      {
        "netbasalinsulin": 0.85, 
        "activity": 0.0046, 
        "basaliob": 0.027, 
        "time": "2016-05-07T03:08:04.000Z", 
        "hightempinsulin": 0.85, 
        "bolussnooze": 0, 
        "iob": 0.076
      }, 
      {
        "netbasalinsulin": 0.75, 
        "activity": 0.0039, 
        "basaliob": 0.019, 
        "time": "2016-05-07T03:13:04.000Z", 
        "hightempinsulin": 0.75, 
        "bolussnooze": 0, 
        "iob": 0.056
      }, 
      {
        "netbasalinsulin": 0.6, 
        "activity": 0.0032, 
        "basaliob": 0.013, 
        "time": "2016-05-07T03:18:04.000Z", 
        "hightempinsulin": 0.6, 
        "bolussnooze": 0, 
        "iob": 0.04
      }, 
      {
        "netbasalinsulin": 0.5, 
        "activity": 0.0026, 
        "basaliob": 0.009, 
        "time": "2016-05-07T03:23:04.000Z", 
        "hightempinsulin": 0.5, 
        "bolussnooze": 0, 
        "iob": 0.028
      }, 
      {
        "netbasalinsulin": 0.4, 
        "activity": 0.002, 
        "basaliob": 0.006, 
        "time": "2016-05-07T03:28:04.000Z", 
        "hightempinsulin": 0.4, 
        "bolussnooze": 0, 
        "iob": 0.017
      }, 
      {
        "netbasalinsulin": 0.3, 
        "activity": 0.0015, 
        "basaliob": 0.004, 
        "time": "2016-05-07T03:33:04.000Z", 
        "hightempinsulin": 0.3, 
        "bolussnooze": 0, 
        "iob": 0.01
      }, 
      {
        "netbasalinsulin": 0.2, 
        "activity": 0.001, 
        "basaliob": 0.002, 
        "time": "2016-05-07T03:38:04.000Z", 
        "hightempinsulin": 0.2, 
        "bolussnooze": 0, 
        "iob": 0.005
      }, 
      {
        "netbasalinsulin": 0.2, 
        "activity": 0.0006, 
        "basaliob": 0.001, 
        "time": "2016-05-07T03:43:04.000Z", 
        "hightempinsulin": 0.2, 
        "bolussnooze": 0, 
        "iob": 0.002
      }, 
      {
        "netbasalinsulin": 0.1, 
        "activity": 0.0002, 
        "basaliob": 0.001, 
        "time": "2016-05-07T03:48:04.000Z", 
        "hightempinsulin": 0.1, 
        "bolussnooze": 0, 
        "iob": 0
      }
    ], 
    "enacted": {
      "bg": 154, 
      "temp": "absolute", 
      "snoozeBG": 92, 
      "recieved": true, 
      "predBGs": {
        "aCOB": [
          154, 
          155, 
          156, 
          157, 
          157, 
          157, 
          156, 
          156, 
          155, 
          153, 
          152, 
          151, 
          149, 
          148, 
          145, 
          143, 
          140, 
          137, 
          135, 
          132, 
          129, 
          126, 
          124, 
          121, 
          118, 
          115, 
          113, 
          110, 
          109, 
          107, 
          106, 
          105, 
          104, 
          103
        ], 
        "IOB": [
          154, 
          146, 
          138, 
          129, 
          121, 
          113, 
          105, 
          97, 
          89, 
          81, 
          74, 
          67, 
          61, 
          54, 
          47, 
          41, 
          39
        ]
      }, 
      "reason": "COB: 25, Dev: -1, BGI: -2.76, Target: 80; Eventual BG 21<80, bolus snooze: eventual BG range 21-92; setting current basal of 0.5 as temp", 
      "rate": 0.5, 
      "eventualBG": 21, 
      "timestamp": "2016-05-07T00:55:07.000Z", 
      "duration": 30, 
      "tick": -9
    }
  }, 
  "mmtune": {
    "scanDetails": [
      [
        "916.560", 
        5, 
        -62
      ], 
      [
        "916.580", 
        5, 
        -57
      ], 
      [
        "916.600", 
        5, 
        -56
      ], 
      [
        "916.620", 
        5, 
        -53
      ], 
      [
        "916.640", 
        5, 
        -52
      ], 
      [
        "916.660", 
        5, 
        -55
      ], 
      [
        "916.680", 
        5, 
        -56
      ], 
      [
        "916.700", 
        5, 
        -62
      ]
    ], 
    "setFreq": 916.64, 
    "timestamp": "2016-05-07T00:53:23.000Z", 
    "usedDefault": false
  }
}